Workbook
Name Produtos: Table_Produtos[PRODUTO]
Name Serviços: Table_Serviços[SERVIÇO]

Sheet To Do
A1: DATE | B1: TASK | C1: OBS | D1: STATUS
A2: 46035 | B2: Add e-mail Cia Beal | D2: DONE
A3: 46126 | B3: Alimentar Base - Serviços & Produtos | D3: DONE
A4: 46038 | B4: Anderson - ASO | C4: Cesla | D4: DONE
A5: 46038 | B5: Anderson - CNH/RG/CPF | C5: Cesla | D5: DONE
A6: 46038 | B6: Anderson - NR12 | C6: Cesla | D6: DONE
A7: 46038 | B7: Anderson - OS/EPI | C7: Cesla | D7: DONE
A8: 46084 | B8: Aprovação - Baston | C8: OS #1555 | D8: DONE
A9: 46072 | B9: Aprovação - Costantini | C9: OS #1533 | D9: DONE
A10: 46072 | B10: Aprovação - Costantini | C10: OS #1534 | D10: DONE
A11: 46055 | B11: Aprovação - Curitiba Business | C11: OS #1265 | D11: DONE
A12: 46057 | B12: Aprovação - Neoortho Thá | C12: OS #1364 | D12: DONE
A13: 46134 | B13: Aprovação - Netcom | C13: OS #1777 | D13: DONE
A14: 46127 | B14: Aprovação - Renault | C14: OS #1757 | D14: DONE
A15: 46105 | B15: Aprovação - Selection | C15: OS #1512 | D15: DONE
... A17: 46071 | B17: Aprovação - Votorantim | C17: OS #1506 | D17: DONE
A18: 46049 | B18: Assinar - Contrato Clinimêrces | D18: DONE
A19: 46079 | B19: Atualizar - Condor São José | C19: OS #1532 | D19: DONE
A20: 46119 | B20: Atualizar - Docs SG3 | D20: DONE
A21: 46042 | B21: Atualizar - Hotel Confiance | C21: OS #1336 | D21: DONE
A22: 46035 | B22: Atualizar - JRM | C22: OS #1364 | D22: DONE
A23: 46073 | B23: Atualizar - Lu cardoso | C23: OS #1544 | D23: DONE
A24: 46079 | B24: Atualizar - Mondelez | C24: OS #1575 | D24: DONE
A25: 46114 | B25: Atualizar - Mondelez | C25: OS #1613 | D25: DONE
A26: 46035 | B26: Atualizar - Mueller | C26: OS #1375 | D26: DONE
A27: 46050 | B27: Atualizar - Oftalmologia | C27: OS #1437 | D27: DONE
A28: 46035 | B28: Atualizar - OS #1120 | C28: OS #1385 | D28: DONE
A29: 46038 | B29: Atualizar - Sesi | C29: 0808/25 - 1054/25 | D29: DONE
A30: 46065 | B30: Atualizar - Sicredi | C30: OS #1254 | D30: DONE
A31: 46036 | B31: Atualizar - Templates email | D31: DONE
A32: 46072 | B32: Atualizar - Tetrapak | C32: OS #1209 | D32: DONE
A33: 46038 | B33: Atualizar - Vencimento Docs | D33: DONE
A34: 46084 | B34: Cadastrar - Calpie | D34: DONE
A35: 46076 | B35: Cadastrar - Jatoba | D35: DONE
A36: 46009 | B36: Cancelar Notas - Lightera | C36: NFS-e 60 | D36: DONE
A37: 46073 | B37: Cancelar Notas - Manusa | C37: OS #5249 | D37: DONE
A38: 46064 | B38: Cancelar Notas - Neoortho | C38: OS #1364 | D38: DONE
A39: 46006 | B39: Cancelar Notas - Rissi | C39: NF-e 5381 | D39: DONE
A40: 46065 | B40: Cancelar Notas - Sicredi | C40: OS #1254 | D40: DONE
A41: 46064 | B41: Carta Correção NF-e 5442 | C41: OS #1254 | D41: DONE
A42: 46077 | B42: Carta Correção NFS-e 5460 | C42: OS #637 | D42: DONE
A43: 46035 | B43: Carta Correção NFS-e 62 | C43: OS #1328 | D43: DONE
A44: 46064 | B44: Contas a Pagar | D44: DONE
A45: 46038 | B45: Docs Integração | D45: DONE
A46: 46076 | B46: Email - Netcom | C46: OS #1351 | D46: DONE
A47: 46050 | B47: Emitir - Multa | C47: Ecosport | D47: DONE
A48: 46077 | B48: Emitir Notas - 4L Serviços | C48: OS # 637 | D48: DONE
A49: 46077 | B49: Emitir Notas - 4L Serviços | C49: OS #1495 | D49: DONE
A50: 46056 | B50: Emitir Notas - 4L Serviços | C50: OS #641 | D50: DONE
A51: 46097 | B51: Emitir Notas - Accor | C51: OS #1646 | D51: DONE
A52: 46128 | B52: Emitir Notas - Accor | C52: OS #1648 | D52: DONE
A53: 46094 | B53: Emitir Notas - All Industria | C53: Estoque | D53: DONE
A54: 46094 | B54: Emitir Notas - All Industria | C54: Porto Feliz | D54: DONE
A55: 46134 | B55: Emitir Notas - All Industria | C55: Remessa Industrialização | D55: DONE
A56: 46134 | B56: Emitir Notas - Alltech | C56: OS #1440 | D56: DONE
A57: 46035 | B57: Emitir Notas - Alumisistem | C57: OS #343 | D57: DONE
... A81: 46134 | B81: Emitir Notas - CS Ospitalita | C81: OS #1768 | D81: DONE
A82: 46050 | B82: Emitir Notas - Devolução | D82: DONE
A83: 46122 | B83: Emitir Notas - Dora | C83: OS #1749 | D83: DONE
A84: 46041 | B84: Emitir Notas - Ebanx | C84: OS #1130 | D84: DONE
A85: 46062 | B85: Emitir Notas - Ebanx | C85: OS #1273 | D85: DONE
A86: 46041 | B86: Emitir Notas - Ebanx | C86: OS #1323 | D86: DONE
A87: 46071 | B87: Emitir Notas - Edimar | C87: OS #1480 | D87: DONE
A88: 46122 | B88: Emitir Notas - EQS | C88: OS #1709 | D88: DONE
A89: 46134 | B89: Emitir Notas - F2W | C89: OS #1756 | D89: DONE
A90: 46072 | B90: Emitir Notas - Filial 11 | C90: OS #1537 | D90: DONE
A91: 46076 | B91: Emitir Notas - Filial 11 | C91: OS #1537 | D91: DONE
A92: 46119 | B92: Emitir Notas - Filial 14 Condor | C92: OS #1733 | D92: DONE
A93: 46072 | B93: Emitir Notas - Filial 24 | C93: OS #1539 | D93: DONE
A94: 46064 | B94: Emitir Notas - Filial 49 | C94: OS #1101 - NICE | D94: DONE
... A102: 46084 | B102: Emitir Notas - Frimesa | C102: OS #1604 / NF-e: 5470 | D102: DONE
A103: 46052 | B103: Emitir Notas - Galvanização | D103: DONE
A104: 46077 | B104: Emitir Notas - Gedanski | C104: OS #1548 | D104: DONE
A105: 46044 | B105: Emitir Notas - Glaser | C105: OS #1412 | D105: DONE
A106: 46084 | B106: Emitir Notas - Grandfood | C106: OS #1588 / NFS-e 114 | D106: DONE
A107: 46106 | B107: Emitir Notas - Gusto & Henri | C107: OS #1694 | D107: DONE
A108: 46101 | B108: Emitir Notas - Hergen | C108: OS #1628 | D108: DONE
A109: 46101 | B109: Emitir Notas - Hergen | C109: OS #1628 | D109: DONE
A110: 46051 | B110: Emitir Notas - Hexion | C110: OS #1450 | D110: DONE
A111: 46077 | B111: Emitir Notas - Hospital Olhos | C111: OS #1544 | D111: DONE
A112: 46009 | B112: Emitir Notas - Hotel 10 | C112: OS #1352 | D112: DONE
A113: 46041 | B113: Emitir Notas - Hotel Curitiba | C113: OS #1369 | D113: DONE
A114: 46106 | B114: Emitir Notas - In Haus | C114: OS #1421 | D114: DONE
A115: 46071 | B115: Emitir Notas - In Haus | C115: OS #1493 | D115: DONE
... A117: 46035 | B117: Emitir Notas - In Haus | C117: OS #1193 | D117: DONE
A118: 46050 | B118: Emitir Notas - Industrialização | D118: DONE
A119: 46038 | B119: Emitir Notas - JJGC | C119: OS #1278 | D119: DONE
A120: 46008 | B120: Emitir Notas - JJGC | C120: OS #1343 | D120: DONE
A121: 46055 | B121: Emitir Notas - JJGC | C121: OS #1411 | D121: DONE
A122: 46119 | B122: Emitir Notas - JM Clean | C122: OS #1556 | D122: DONE
A123: 46129 | B123: Emitir Notas - Jockey | C123: OS #1738 | D123: DONE
A124: 46052 | B124: Emitir Notas - Kharina | C124: OS #1431 | D124: DONE
A125: 46107 | B125: Emitir Notas - Kutassy | C125: OS #1448 | D125: DONE
A126: 46106 | B126: Emitir Notas - Landis+Gyr | C126: OS #1603 | D126: DONE
A127: 46009 | B127: Emitir Notas - Lightera | C127: OS #1340 | D127: DONE
A128: 46035 | B128: Emitir Notas - Lightera | C128: OS #1340 | D128: DONE
A129: 46097 | B129: Emitir Notas - LP Imóveis | C129: OS #1649 | D129: DONE
A130: 46079 | B130: Emitir Notas - MA Goulart | C130: OS #1564 | D130: DONE
... A203: 46129 | B203: Termo Garantia - Mondelez | C203: OS #1744 | D203: DONE
A204: 46038 | B204: Jeferson - OS/EPI | D204: DONE
...

Sheet NC Portas
D1: NF-e PRODUTO | G1: NFS-e SERVIÇO
A2: OS | B2: CLIENTE | C2: TOTAL | D2: NF-e | E2: VALOR | F2: Status P | G2: NFS-e | H2: DPS | I2: VALOR SERVIÇO | J2: Status S | K2: OK | L2: REF | M2: OBSERVAÇÕES
A3: 427 | B3: Sig | C3: 5629 | D3: 5329 | E3: 3379 | F3: Emitida | G3: 5 | H3: 15 | I3: 2250 | J3: Emitida | K3: =IF(AND(D3<>"", G3<>""), "OK", "") -> OK | L3: 0978/25
A4: 431 | B4: Sig | C4: 3842.6 | D4: 5330 | E4: 1722.3 | F4: Emitida | G4: 6 | H4: 18 | I4: 2120 | J4: Emitida | K4: =IF(AND(D4<>"", G4<>""), "OK", "") -> OK | L4: 0977/25
A5: 450 | B5: In Haus | C5: 1280 | D5: - | E5: - | F5: - | G5: 7 | H5: 13 | I5: 1280 | J5: Emitida | K5: =IF(AND(D5<>"", G5<>""), "OK", "") -> OK | L5: 1069/25
A6: 1227 | B6: Triermach | C6: 1613 | D6: 5349 | E6: 723 | F6: Emitida | G6: 8 | H6: 24 | I6: 890 | J6: Emitida | K6: =IF(AND(D6<>"", G6<>""), "OK", "") -> OK | L6: -
A7: 390 | B7: Sig | C7: 3586.3 | D7: 5257 | E7: 1898.8 | F7: Emitida | G7: 9 | H7: 19 | I7: 1687.5 | J7: Emitida | K7: =IF(AND(D7<>"", G7<>""), "OK", "") -> OK | L7: 0845/25
A8: 1096 | B8: In Haus | C8: 1588 | D8: 5353 | E8: 698 | F8: Emitida | G8: 12 | H8: 27 | I8: 890 | J8: Emitida | K8: =IF(AND(D8<>"", G8<>""), "OK", "") -> OK | L8: -
A9: 55 | B9: Mondelez | C9: 28360.9 | D9: 5011 | E9: 22940.9 | F9: Emitida | G9: 13 | H9: 28 | I9: 5420 | J9: Emitida | K9: =IF(AND(D9<>"", G9<>""), "OK", "") -> OK | L9: 0115/25
A10: 317 | B10: Mondelez | C10: 1590 | D10: - | E10: - | F10: - | G10: 14 | H10: 29 | I10: 1590 | J10: Emitida | K10: =IF(AND(D10<>"", G10<>""), "OK", "") -> OK | L10: 0317/25
A11: 365 | B11: Volkswagen | C11: 32346.3 | D11: 5328 | E11: 27751.3 | F11: Emitida | G11: 15 | H11: 7 | I11: 4595 | J11: Cancelada | K11: OK | L11: 0455/25 | M11: Cancelada e reemitida na OS #1276
A12: 401 | B12: Mondelez | C12: 33341.4 | D12: 5347 | E12: 27681.4 | F12: Emitida | G12: 17 | H12: 31 | I12: 5660 | J12: Emitida | K12: =IF(AND(D12<>"", G12<>""), "OK", "") -> OK | L12: 0947/25
A13: 1250 | B13: DVS | C13: 890 | D13: - | E13: - | F13: - | G13: 18 | H13: 32 | I13: 890 | J13: Emitida | K13: =IF(AND(D13<>"", G13<>""), "OK", "") -> OK | L13: -
A14: 424 | B14: API SPE 46 | C14: 26180 | D14: 5354 | E14: 10820 | F14: Emitida | G14: 19 | H14: 33 | I14: 15360 | J14: Emitida | K14: =IF(AND(D14<>"", G14<>""), "OK", "") -> OK | L14: 1015/25 | M14: 1006/25
A15: 436 | B15: Renault | C15: 5180 | D15: 5351 | E15: 3360 | F15: Emitida | G15: 21 | H15: 35 | I15: 1820 | J15: Emitida | K15: =IF(AND(D15<>"", G15<>""), "OK", "") -> OK | L15: 1051/25
A16: 1044 | B16: In Haus | C16: 1126.76 | D16: - | E16: - | F16: - | G16: 22 | H16: 36 | I16: 1126.76 | J16: Emitida | K16: =IF(AND(D16<>"", G16<>""), "OK", "") -> OK | L16: -
A17: 1185 | B17: In Haus | C17: 1790 | D17: - | E17: - | F17: - | G17: 23 | H17: 37 | I17: 1790 | J17: Emitida | K17: =IF(AND(D17<>"", G17<>""), "OK", "") -> OK | L17: -
A18: 1123 | B18: Mondelez | C18: 29734.3 | D18: 5346 | E18: 23314.3 | F18: Emitida | G18: 24 | H18: 38 | I18: 6420 | J18: Emitida | K18: =IF(AND(D18<>"", G18<>""), "OK", "") -> OK | L18: -
A19: 770 | B19: Gold | C19: 10560 | D19: 5355 | E19: 5460 | F19: Emitida | G19: 26 | H19: 11 | I19: 4284 | J19: Emitida | K19: =IF(AND(D19<>"", G19<>""), "OK", "") -> OK | L19: -
A20: 1263 | B20: Liga das Senhoras | C20: 890 | D20: - | E20: - | F20: - | G20: 28 | H20: 41 | I20: 890 | J20: Emitida | K20: =IF(AND(D20<>"", G20<>""), "OK", "") -> OK | L20: -
A21: 1145 | B21: Ebanx | C21: 16247.15 | D21: 5359 | E21: 6447.15 | F21: Emitida | G21: 29 | H21: 42 | I21: 9800 | J21: Emitida | K21: =IF(AND(D21<>"", G21<>""), "OK", "") -> OK | L21: -
A22: 1251 | B22: Callfarma | C22: 1720 | D22: 5360 | E22: 830 | F22: Emitida | G22: 30 | H22: 43 | I22: 890 | J22: Emitida | K22: =IF(AND(D22<>"", G22<>""), "OK", "") -> OK | L22: -
A23: 1248 | B23: Hospital Union | C23: 980 | D23: - | E23: - | F23: - | G23: 31 | H23: 44 | I23: 980 | J23: Emitida | K23: =IF(AND(D23<>"", G23<>""), "OK", "") -> OK | L23: -
A24: 280 | B24: Graham Pack | C24: 32138.53 | D24: 5248 | E24: 29138.53 | F24: Emitida | G24: 32 | H24: 46 | I24: 3000 | J24: Emitida | K24: =IF(AND(D24<>"", G24<>""), "OK", "") -> OK | L24: 0989/24
A25: 1276 | B25: Volkswagen | C25: 32346.3 | D25: - | E25: - | F25: - | G25: 33 | H25: 13 | I25: 32346.3 | J25: Emitida | K25: =IF(AND(D25<>"", G25<>""), "OK", "") -> OK | L25: 365
A26: 1283 | B26: Filial 28 - Condor | C26: 920 | D26: - | E26: - | F26: - | G26: 36 | H26: 51 | I26: 920 | J26: Emitida | K26: =IF(AND(D26<>"", G26<>""), "OK", "") -> OK | L26: -
A27: 1284 | B27: Filial 01 - Condor | C27: 1315.7 | D27: 5374 | E27: 665.7 | F27: Emitida | G27: 37 | H27: 52 | I27: 650 | J27: Emitida | K27: =IF(AND(D27<>"", G27<>""), "OK", "") -> OK | L27: -
A28: 327 | B28: Renault | C28: 6468.4 | D28: 5200 | E28: 2918.4 | F28: Emitida | G28: 38 | H28: 15 | I28: 3550 | J28: Emitida | K28: =IF(AND(D28<>"", G28<>""), "OK", "") -> OK | L28: 0645/25
A29: 976 | B29: Sig | C29: 1442.5 | D29: - | E29: - | F29: - | G29: 39 | H29: 17 | I29: 1442.5 | J29: Emitida | K29: =IF(AND(D29<>"", G29<>""), "OK", "") -> OK | L29: -
A30: 399 | B30: Renault | C30: 7644.5 | D30: 5371 | E30: 1333.2 | F30: Emitida | G30: 40 | H30: 19 | I30: 6311.3 | J30: Emitida | K30: =IF(AND(D30<>"", G30<>""), "OK", "") -> OK | L30: 0646/25
A31: 1259 | B31: Hospital Santa Cruz | C31: 890 | D31: - | E31: - | F31: - | G31: 41 | H31: 53 | I31: 890 | J31: Emitida | K31: =IF(AND(D31<>"", G31<>""), "OK", "") -> OK | L31: -
A32: 1287 | B32: Centro Empresarial Glaser | C32: 890 | D32: - | E32: - | F32: - | G32: 42 | H32: 54 | I32: 890 | J32: Emitida | K32: =IF(AND(D32<>"", G32<>""), "OK", "") -> OK | L32: -
A33: 1272 | B33: L&F Vidros | C33: 6160 | D33: 5376 | E33: 1240 | F33: Cancelada | G33: 43 | H33: 55 | I33: 4920 | J33: Cancelada | K33: OFF | L33: - | M33: Cancelada
A34: 418 | B34: L&F Vidros | C34: 7445 | D34: 5377 | E34: 1180 | F34: Cancelada | G34: 44 | H34: 56 | I34: 6265 | J34: Cancelada | K34: OFF | L34: 0945/25 | M34: Cancelada
A35: 1272 | B35: L&F Vidros | C35: 6160 | D35: 5376 | E35: 1240 | F35: Cancelada | G35: 45 | H35: 21 | I35: 4674 | J35: Cancelada | K35: OFF | L35: - | M35: Cancelada
A36: 418 | B36: L&F Vidros | C36: 7445 | D36: 5377 | E36: 1180 | F36: Cancelada | G36: 46 | H36: 23 | I36: 5951.75 | J36: Cancelada | K36: OFF | L36: - | M36: Cancelada
A37: 1269 | B37: JJGC | C37: 890 | D37: - | E37: - | F37: - | G37: 47 | H37: 57 | I37: 890 | J37: Emitida | K37: =IF(AND(D37<>"", G37<>""), "OK", "") -> OK | L37: -
A38: 332 | B38: JJGC | C38: 33874.91 | D38: 5372 | E38: 28469.41 | F38: Emitida | G38: 49 | H38: 58 | I38: 5405.5 | J38: Emitida | K38: =IF(AND(D38<>"", G38<>""), "OK", "") -> OK | L38: 0593/25
A39: 1118 | B39: JJGC | C39: 17644.3 | D39: 5369 | E39: 12901 | F39: Emitida | G39: 50 | H39: 59 | I39: 4743.3 | J39: Emitida | K39: =IF(AND(D39<>"", G39<>""), "OK", "") -> OK
A40: 1272 | B40: L&F Vidros | C40: 6160 | D40: 5378 | E40: 1240 | F40: Emitida | G40: 51 | H40: 25 | I40: 4132.8 | J40: Emitida | K40: =IF(AND(D40<>"", G40<>""), "OK", "") -> OK | L40: -
A41: 418 | B41: L&F Vidros | C41: 7445 | D41: 5379 | E41: 1180 | F41: Emitida | G41: 52 | H41: 27 | I41: 5262.6 | J41: Emitida | K41: =IF(AND(D41<>"", G41<>""), "OK", "") -> OK | L41: 0945/25
A42: 636 | B42: 4L Serviços | C42: 12523 | D42: 5385 | E42: 7443 | F42: Emitida | G42: 53 | H42: 60 | I42: 5080 | J42: Emitida | K42: =IF(AND(D42<>"", G42<>""), "OK", "") -> OK | L42: -
A43: 1291 | B43: Hospital Santa Cruz | C43: 890 | D43: - | E43: - | F43: - | G43: 54 | H43: 61 | I43: 890 | J43: Emitida | K43: =IF(AND(D43<>"", G43<>""), "OK", "") -> OK | L43: -
A44: 1225 | B44: M.A. Goulart | C44: 5710.8 | D44: 5389 | E44: 380.8 | F44: Emitida | G44: 55 | H44: 29 | I44: 5330 | J44: Emitida | K44: =IF(AND(D44<>"", G44<>""), "OK", "") -> OK | L44: -
A45: 1326 | B45: Farmácia Pavesi | C45: 890 | D45: - | E45: - | F45: - | G45: 56 | H45: 63 | I45: 890 | J45: Emitida | K45: =IF(AND(D45<>"", G45<>""), "OK", "") -> OK | L45: -
A46: 983 | B46: NB Engenharia | C46: 10685 | D46: 5383 | E46: 6205 | F46: Emitida | G46: 57 | H46: 31 | I46: 4480 | J46: Emitida | K46: =IF(AND(D46<>"", G46<>""), "OK", "") -> OK | L46: -
A47: 393 | B47: Sig | C47: 7558 | D47: 5292 | E47: 6038 | F47: Emitida | G47: 58 | H47: 33 | I47: 1520 | J47: Emitida | K47: =IF(AND(D47<>"", G47<>""), "OK", "") -> OK | L47: 0982/25
A48: 1343 | B48: JJGC | C48: 9344.06 | D48: 5393 | E48: 8454.06 | F48: Emitida | G48: 59 | H48: 64 | I48: 890 | J48: Emitida | K48: =IF(AND(D48<>"", G48<>""), "OK", "") -> OK | L48: -
A49: 1340 | B49: Lightera | C49: 890 | D49: - | E49: - | F49: - | G49: 60 | H49: 65 | I49: 890 | J49: Cancelada | K49: OFF | L49: - | M49: Cancelada
A50: 1328 | B50: PGE/PR | C50: 2930 | D50: - | E50: - | F50: - | G50: 61 | H50: 66 | I50: 2930 | J50: Cancelada | K50: OFF | L50: - | M50: Cancelada
A51: 1328 | B51: PGE/PR | C51: 2930 | D51: - | E51: - | F51: - | G51: 62 | H51: 37 | I51: 2930 | J51: Substituida | K51: OFF | L51: - | M51: Substituida
A52: 1352 | B52: Hotel 10 | C52: 1540 | D52: 5397 | E52: 590 | F52: Emitida | G52: 63 | H52: 68 | I52: 950 | J52: Emitida | K52: =IF(AND(D52<>"", G52<>""), "OK", "") -> OK | L52: -
A53: 1172 | B53: Cia Beal | C53: 1945 | D53: 5400 | E53: 995 | F53: Emitida | G53: 64 | H53: 69 | I53: 950 | J53: Emitida | K53: =IF(AND(D53<>"", G53<>""), "OK", "") -> OK | L53: -
A54: 1172 | B54: Cia Beal | C54: 1945 | D54: 5427 | E54: 995 | F54: Emitida | G54: 64 | H54: 69 | I54: 950 | J54: Emitida | K54: OK | L54: 5400 | M54: Devolução NF-e: 5400
A55: 1172 | B55: Associação Franciscana | C55: 1945 | D55: 5433 | E55: 995 | F55: Emitida | G55: 64 | H55: 69 | I55: 950 | J55: Emitida | K55: OK | L55: -
A56: 1293 | B56: Associação Franciscana | C56: 1068 | D56: 5401 | E56: 178 | F56: Emitida | G56: 65 | H56: 39 | I56: 747.6 | J56: Emitida | K56: =IF(AND(D56<>"", G56<>""), "OK", "") -> OK | L56: -
A57: 1293 | B57: Associação Franciscana | C57: 1068 | D57: 5428 | E57: 178 | F57: Emitida | G57: 65 | H57: 39 | I57: 890 | J57: Emitida | K57: OK | L57: 5401 | M57: Devolução NF-e: 5401
A58: 1293 | B58: Cia Beal | C58: 1068 | D58: 5434 | E58: 178 | F58: Emitida | G58: 65 | H58: 39 | I58: 747.6 | J58: Emitida | K58: OK | L58: - | M58: Retenção ISS/INSS
A59: 1328 | B59: PGE/PR | C59: 2930 | D59: - | E59: - | F59: - | G59: 66 | H59: 41 | I59: 2930 | J59: Emitida | K59: OK | L59: 62/37
A60: 343 | B60: Alumisistem | C60: 12090 | D60: - | E60: - | F60: - | G60: 67 | H60: 43 | I60: 12090 | J60: Emitida | K60: OK | L60: 0463/25
A61: 1340 | B61: Lightera | C61: 890 | D61: - | E61: - | F61: - | G61: 68 | H61: 47 | I61: 890 | J61: Emitida | K61: OK | L61: -
A62: 1174 | B62: Onet Engenharia | C62: 2243.6 | D62: 5404 | E62: 1353.6 | F62: Emitida | G62: 69 | H62: 49 | I62: 890 | J62: Emitida | K62: OK
A63: 1193 | B63: In Haus | C63: 27710.5 | D63: 5396 | E63: 23420.5 | F63: Emitida | G63: 70 | H63: 53 | I63: 4290 | J63: Emitida | K63: =IF(AND(D63<>"", G63<>""), "OK", "") -> OK | L63: - | M63: Retenção ISS/INSS
A64: 1375 | B64: Casc | C64: 2550 | D64: - | E64: - | F64: - | G64: 71 | H64: 55 | I64: 2550 | J64: Emitida | K64: OK
A65: 1323 | B65: Ebanx | C65: 2100 | D65: 5408 | E65: 1650 | F65: Emitida | G65: 72 | H65: 57 | I65: 450 | J65: Emitida | K65: OK | L65: -
A66: 1130 | B66: Ebanx | C66: 6763 | D66: 5409 | E66: 3073 | F66: Emitida | G66: 73 | H66: 59 | I66: 3690 | J66: Emitida | K66: OK | L66: 1145
A67: 1369 | B67: Hotel Curitiba | C67: 890 | D67: - | E67: - | F67: - | G67: 74 | H67: 61 | I67: 890 | J67: Emitida | K67: OK | L67: -
A68: 916 | B68: Baggio | C68: 24146.1 | D68: 5410 | E68: 13006.1 | F68: Emitida | G68: 75 | H68: 63 | I68: 11140 | J68: Emitida | K68: OK | M68: Retenção ISS/INSS
A69: 984 | B69: NB Engenharia | C69: 19700 | D69: 5411 | E69: 12410 | F69: Emitida | G69: 76 | H69: 65 | I69: 7290 | J69: Cancelada | K69: OFF | L69: - | M69: Cancelada NFS-e: 76
A70: 866 | B70: Fundação PIO XII | C70: 33440 | D70: 5412 | E70: 22220 | F70: Emitida | G70: 77 | H70: 67 | I70: 11220 | J70: Cancelada | K70: OFF | L70: - | M70: Cancelada NFS-e: 77
A71: - | B71: Manusa | C71: 8279.04 | D71: - | E71: - | F71: - | G71: 78 | H71: 69 | I71: 8279.04 | J71: Emitida | K71: OK | L71: - | M71: Comissão
A72: 1414 | B72: Quick Burger | C72: 801 | D72: - | E72: - | F72: - | G72: 79 | H72: 71 | I72: 801 | J72: Emitida | K72: OK | L72: -
A73: 1412 | B73: Centro Empresarial Glaser | C73: 4299 | D73: 5414 | E73: 2519 | F73: Emitida | G73: 80 | H73: 78 | I73: 1780 | J73: Emitida | K73: OK | L73: -
A74: 1292 | B74: Rinaldi | C74: 3735 | D74: 5415 | E74: 2445.42 | F74: Emitida | G74: 81 | H74: 80 | I74: 1289.58 | J74: Cancelada | K74: OK | L74: - | M74: Cancelada NFS-e
A75: 1292 | B75: Rinaldi | C75: 3735 | D75: 5415 | E75: 2445.42 | F75: Emitida | G75: 82 | H75: 83 | I75: 1225.1 | J75: Substituida | K75: OFF | L75: - | M75: Retenção ISS/Substituida
A76: 1409 | B76: Filial 51 - Condor | C76: 3874.5 | D76: 5416 | E76: 1244.5 | F76: Emitida | G76: 83 | H76: 85 | I76: 2498.5 | J76: Emitida | K76: OK | L76: - | M76: Retenção ISS
A77: 1416 | B77: Trelrium | C77: 890 | D77: - | E77: - | F77: - | G77: 84 | H77: 87 | I77: 890 | J77: Emitida | K77: OK | L77: -
A78: 1346 | B78: Onet Engenharia | C78: 2246 | D78: 5421 | E78: 1356 | F78: Emitida | G78: 85 | H78: 89 | I78: 890 | J78: Emitida | K78: OK | L78: -
A79: 1334 | B79: Mapa | C79: 2689.79 | D79: 5423 | E79: 189.79 | F79: Emitida | G79: 86 | H79: 91 | I79: 2500 | J79: Substituida | K79: OK | L79: - | M79: Substituida NFS-e
A80: 1292 | B80: Rinaldi | C80: 3735 | D80: 5415 | E80: 2445.42 | F80: Emitida | G80: 87 | H80: 93 | I80: 1255.1 | J80: Emitida | K80: OK | L80: - | M80: Retenção ISS
A81: 1450 | B81: Hexion | C81: 890 | D81: - | E81: - | F81: - | G81: 88 | H81: 95 | I81: 890 | J81: Emitida | K81: OK | L81: -
A82: 1431 | B82: Quick Burger | C82: 2188.45 | D82: 5430 | E82: 1377.45 | F82: Emitida | G82: 89 | H82: 97 | I82: 900 | J82: Emitida | K82: OK | L82: -
A83: 1334 | B83: Mapa | C83: 2689.79 | D83: 5423 | E83: 189.79 | F83: Emitida | G83: 90 | H83: 99 | I83: 2500 | J83: Emitida | K83: OK | L83: -
A84: 1411 | B84: JJGC | C84: 890 | D84: - | E84: - | F84: - | G84: 91 | H84: 101 | I84: 890 | J84: Emitida | K84: OK | L84: -
A85: 866 | B85: Fundação PIO XII | C85: 33440 | D85: 5412 | E85: 22220 | F85: Emitida | G85: 92 | H85: 103 | I85: 11220 | J85: Emitida | K85: OK | L85: -
A86: 984 | B86: NB Engenharia | C86: 19700 | D86: 5411 | E86: 12410 | F86: Emitida | G86: 93 | H86: 105 | I86: 7290 | J86: Emitida | K86: OK | L86: -
A87: 641 | B87: 4L Serviços | C87: 16175 | D87: 5435 | E87: 9145 | F87: Emitida | G87: 94 | H87: 107 | I87: 7030 | J87: Emitida | K87: OK | L87: - | M87: Retenção/ISS
A88: 1336 | B88: Centro Civico Apart | C88: 11806 | D88: 5431 | E88: 7996 | F88: Emitida | G88: 95 | H88: 1 | I88: 3810 | J88: Emitida | K88: OK
A89: 1496 | B89: Lanchonete Garcport | C89: 845.5 | D89: - | E89: - | F89: - | G89: 96 | H89: 2 | I89: 845.5 | J89: Emitida | K89: OK | L89: -
A90: 1351 | B90: Netcom Construtora Ltda | C90: 15569 | D90: 5448 | E90: 8149 | F90: Emitida | G90: 101 | H90: 8 | I90: 7420 | J90: Emitida | K90: OK
A91: 1270 | B91: Edifício Business Center | C91: 1300 | D91: 542 | E91: 1300 | F91: Emitida | G91: - | H91: - | I91: - | J91: - | K91: OK
A92: 1201 | B92: Memphis | C92: 1342.45 | D92: 5331 | E92: 1342.45 | F92: Emitida | G92: - | H92: - | I92: - | J92: - | K92: OK | L92: -
A93: 1192 | B93: Filial 17 - Condor | C93: 3907.1 | D93: 5342 | E93: 1566.5 | F93: Emitida | G93: - | H93: - | I93: - | J93: - | K93: =IF(AND(D93<>"", G93<>""), "OK", "") -> OK | L93: -
A94: 1192 | B94: Filial 17 - Condor | C94: 3907.1 | D94: 5343 | E94: 2340.6 | F94: Emitida | G94: - | H94: - | I94: - | J94: - | K94: =IF(AND(D94<>"", G94<>""), "OK", "") -> OK | L94: -
A95: 1228 | B95: Filial 17 - Condor | C95: 6273.54 | D95: 5348 | E95: 6273.54 | F95: Emitida | G95: - | H95: - | I95: - | J95: - | K95: =IF(AND(D95<>"", G95<>""), "OK", "") -> OK | L95: -
A96: 1253 | B96: DVS | C96: 4236 | D96: 5358 | E96: 4236 | F96: Emitida | G96: - | H96: - | I96: - | J96: - | K96: =IF(AND(D96<>"", G96<>""), "OK", "") -> OK | L96: -
A97: 1271 | B97: Liga das Senhoras | C97: 1865.7 | D97: 5365 | E97: 1865.7 | F97: Emitida | G97: - | H97: - | I97: - | J97: - | K97: =IF(AND(D97<>"", G97<>""), "OK", "") -> OK | L97: -
A98: 1241 | B98: Triermach | C98: 5111.3 | D98: 5366 | E98: 5111.3 | F98: Emitida | G98: - | H98: - | I98: - | J98: - | K98: =IF(AND(D98<>"", G98<>""), "OK", "") -> OK | L98: -
A99: - | B99: Renault | C99: 5000 | D99: 5370 | E99: 5000 | F99: Emitida | G99: - | H99: - | I99: - | J99: - | K99: =IF(AND(D99<>"", G99<>""), "OK", "") -> OK | L99: - | M99: Retorno
A100: 1285 | B100: Filial 28 - Condor | C100: 5372.64 | D100: 5373 | E100: 5372.64 | F100: Emitida | G100: - | H100: - | I100: - | J100: - | K100: =IF(AND(D100<>"", G100<>""), "OK", "") -> OK | L100: -
...

Sheet Formulas
A1: PRODUTO | E1: TEXT | G1: DESCRIÇÃO | H1: FORMULA
A2: Vidro Temperado Incolor 10mm | E2: ANDAR 01 COND NEW ZEALAND EMPRESAR | G2: Formula Calculo Valor Total m² | H2: Valor Total m² = Area Total m² * Valor m²
A3: VALOR M² | E3: Proper | G3: Formula Calculo Area Total m² | H3: Area Total m² = Largura * Comprimento
A4: MEDIDAS | B4: VALOR | C4: X 2 | E4: =PROPER($E$2) -> Andar 01 Cond New Zealand Empresar | G4: Formula Deslocamento | H4: Distância Km * 2 * 3
A5: Largura | B5: 2.4 | C5: =B5*2 -> 4.8 | E5: lower | G5: Formula Calculo Peso Vidro | H5: Peso Total = Largura * Comprimento * Espessura/kg
A6: Comprimento | B6: 2.2 | C6: =B6*2 -> 4.4 | E6: =LOWER($E$2) -> andar 01 cond new zealand empresar | G6: Formula Calculo PVC | H6: (Largura/2) * Altura * Valor m²
A7: Espessura/kg | B7: =IFERROR(VLOOKUP($C$8,Valor_M²[],3,FALSE),"-") -> - | C7: - | E7: UPPER | G7: Formula Acomodação | H7: ((350 * Dias) + (100 * Dias * Func)) * (1 + 10 %)
A8: Area Total m² | B8: =IFERROR(B5*B6," ") -> 5.28 | C8: =B8*2 -> 10.56 | E8: =UPPER($E$2) -> ANDAR 01 COND NEW ZEALAND EMPRESAR | G8: Custo Serviço Prestado | H8: (Funcionários * Horas * CHH) + (Horas * CHV) + (KM * Valor KM) + Materiais
A9: Valor m² | B9: =IFERROR(VLOOKUP(A2,Valor_M²[#All],2,),"-") -> 470 | C9: =B9*2 -> 940 | G9: Custo Hora Homem | H9: (Folha + Encargos) / Horas Produtivas
A10: Valor Total m² | B10: =IFERROR(B8*B9," ") -> 2481.6 | C10: =B10*2 -> 4963.2 | G10: Custo Hora Veiculo | H10: (Manutenção + Depreciação) / Horas Produtivas
A11: Peso Total Vidro | B11: =IFERROR($D$12*$D$13*$D$14," ") -> 0 | C11: =B11*2 -> 0
A13: DESLOCAMENTO | C13: X 2 | E13: CSP
A14: Distância KM: | B14: 500 | C14: =B14*2 -> 1000 | E14: =_xlfn.LET(_xlpm.V_Folha,CSP!$B$26,_xlpm.V_Frota,CSP!$B$27,_xlpm.H_Produtiva,CSP!$B$28,_xlpm.K_Valor,CSP!$B$29,_xlpm.P_Imposto,CSP!$B$30,_xlpm.S_Quant,CSP!$B$31,_xlpm.S_Horas,CSP!$B$32,_xlpm.S_Dist,CSP!$B$33,_xlpm.S_Mat,CSP!$B$34,_xlpm.CHH,_xlpm.V_Folha/_xlpm.H_Produtiva,_xlpm.CHV,_xlpm.V_Frota/_xlpm.H_Produtiva,_xlpm.Custo_Base,(_xlpm.S_Quant*_xlpm.S_Horas*_xlpm.CHH)+(_xlpm.S_Horas*_xlpm.CHV)+(_xlpm.S_Dist*_xlpm.K_Valor)+_xlpm.S_Mat,_xlpm.CSP_Final,_xlpm.Custo_Base/(1-_xlpm.P_Imposto),_xlpm.CSP_Final) -> 1210.2277
A15: Valor: | B15: =B14*2*3 -> 3000 | C15: =B15*2 -> 6000
A17: CSP
A18: Funcionários | B18: 2
A19: Horas | B19: 8
A20: Distância | B20: 10
A21: Material | B21: 50
A23: ACOMODAÇÃO
A24: Dias | B24: 3
A25: Funcionários | B25: 2
A26: Valor | B26: =((350*B24)+(100*B24*B25))*(1+10%) -> 1815
A28: PVC
A29: Valor: | B29: =IFERROR((B5/2)*B6*B9," ") -> 1240.8
A31: PORCENTAGEM | B31: ADD | C31: DISCOUNT
A32: Valor: | B32: 546 | C32: =B32 -> 546
A33: Porcentagem | B33: 0.1 | C33: 0.05
A34: Total | B34: =B32*(1+B33) -> 600.6 | C34: =C32*(1-C33) -> 518.7
A36: OS | B36: NF | C36: STATUS
A37: 1474 | B37: {=_xlfn.UNIQUE(_xlfn._xlws.FILTER(_xlfn.CHOOSECOLS(_xlfn.VSTACK(NFe_NC[],NFSe_NC[],NFe_Nice[],NFSe_Nice[]),4),_xlfn.CHOOSECOLS(_xlfn.VSTACK(NFe_NC[],NFSe_NC[],NFe_Nice[],NFSe_Nice[]),1)=A37,"No NF Found"))} -> 168 | C37: {=_xlfn.MAP(_xlfn.ANCHORARRAY(B37), _xlfn.LAMBDA(_xlpm.nfe, IF(_xlpm.nfe="No NF-e Found", "", _xlfn.LET( _xlpm.all_data, _xlfn.VSTACK( _xlfn.CHOOSECOLS(NFe_NC[], 4, 10), _xlfn.CHOOSECOLS(NFe_Nice[], 4, 10), _xlfn.CHOOSECOLS(NFSe_NC[], 4, 9), _xlfn.CHOOSECOLS(NFSe_Nice[], 4, 9) ), _xlfn.XLOOKUP(_xlpm.nfe, _xlfn.CHOOSECOLS(_xlpm.all_data, 1), _xlfn.CHOOSECOLS(_xlpm.all_data, 2), "No STATUS Found") ) ) ))} -> Emitida

Sheet Preços
A2: PRODUTOS | C2: Preço Máximo | D2: =_xlfn.MAXIFS(Table_Produtos[V. UNIT],Table_Produtos[PRODUTO],$A$3) -> 774 | J2: SERVIÇOS | L2: Preço Máximo | M2: =_xlfn.MAXIFS(Table_Serviços[V. UNIT],Table_Serviços[SERVIÇO],$J$3) -> 1620
A3: CORREIA DE TRAÇÃO 14MM - BRAVO / VISIO+ 125 | C3: Preço Médio | D3: =AVERAGEIF(Table_Produtos[PRODUTO],$A$3,Table_Produtos[V. UNIT]) -> 774 | J3: SERVIÇO DE PINTURA / ANODIZAÇÃO DE OPERADOR / FOLHA | L3: Preço Médio | M3: =AVERAGEIF(Table_Serviços[SERVIÇO],$J$3,Table_Serviços[V. UNIT]) -> 758.61702
C4: Preço Minimo | D4: =_xlfn.MINIFS(Table_Produtos[V. UNIT],Table_Produtos[PRODUTO],$A$3) -> 774 | L4: Preço Minimo | M4: =_xlfn.MINIFS(Table_Serviços[V. UNIT],Table_Serviços[SERVIÇO],$J$3) -> 430
A6: PRODUTO | B6: UND | C6: QTDE. | D6: NCM | E6: V. UNIT. | F6: V. TOTAL | G6: CLIENTE | H6: OS | J6: SERVIÇO | K6: QTDE | L6: V. UNIT. | M6: V. TOTAL | N6: CLIENTE | O6: OS
A7: {=_xlfn._xlws.SORT(_xlfn._xlws.FILTER(Table_Produtos[],Table_Produtos[PRODUTO]=$A$3,"error"),5,-1)} -> CORREIA DE TRAÇÃO 14MM - BRAVO / VISIO+ 125 | B7: (Un) | C7: 1 | D7: 40029990 | E7: 774 | F7: 774 | G7: EQS Engenharia | H7: 1771 | J7: {=_xlfn._xlws.SORT(_xlfn._xlws.FILTER(Table_Serviços[],Table_Serviços[SERVIÇO]=$J$3,"error"),3,-1)} -> SERVIÇO DE PINTURA / ANODIZAÇÃO DE OPERADOR / FOLHA | K7: 1.00 | L7: 1620 | M7: 1620 | N7: Irmãos Madalosso | O7: 1754
A8: CORREIA DE TRAÇÃO 14MM - BRAVO / VISIO+ 125 | B8: (Un) | C8: 1 | D8: 40029990 | E8: 774 | F8: 774 | G8: Multi Turbo | H8: 1803 | J8: SERVIÇO DE PINTURA / ANODIZAÇÃO DE OPERADOR / FOLHA | K8: 1.00 | L8: 1390 | M8: 1390 | N8: Rissi Fachadas | O8: 1802
J9: SERVIÇO DE PINTURA / ANODIZAÇÃO DE OPERADOR / FOLHA | K9: 1.00 | L9: 1230 | M9: 1230 | N9: Irmãos Madalosso | O9: 1755
J10: SERVIÇO DE PINTURA / ANODIZAÇÃO DE OPERADOR / FOLHA | K10: 1.00 | L10: 1150 | M10: 1150 | N10: Supermercado Jacomar | O10: 1707
J11: SERVIÇO DE PINTURA / ANODIZAÇÃO DE OPERADOR / FOLHA | K11: 1.00 | L11: 980 | M11: 980 | N11: Supermercado Jacomar | O11: 1706
J12: SERVIÇO DE PINTURA / ANODIZAÇÃO DE OPERADOR / FOLHA | K12: 1.00 | L12: 890 | M12: 890 | N12: Selection Locadora | O12: 1701
J13: SERVIÇO DE PINTURA / ANODIZAÇÃO DE OPERADOR / FOLHA | K13: 1.00 | L13: 890 | M13: 890 | N13: Rissi Fachadas | O13: 1750
J14: SERVIÇO DE PINTURA / ANODIZAÇÃO DE OPERADOR / FOLHA | K14: 1.00 | L14: 890 | M14: 890 | N14: Irmãos Madalosso | O14: 1752
J15: SERVIÇO DE PINTURA / ANODIZAÇÃO DE OPERADOR / FOLHA | K15: 1.00 | L15: 890 | M15: 890 | N15: Irmãos Madalosso | O15: 1753
J16: SERVIÇO DE PINTURA / ANODIZAÇÃO DE OPERADOR / FOLHA | K16: 1.00 | L16: 890 | M16: 890 | N16: Vidraçaria Passarela | O16: 1790
J17: SERVIÇO DE PINTURA / ANODIZAÇÃO DE OPERADOR / FOLHA | K17: 1.00 | L17: 850 | M17: 850 | N17: Lavitta Engenharia | O17: 1764
J18: SERVIÇO DE PINTURA / ANODIZAÇÃO DE OPERADOR / FOLHA | K18: 1.00 | L18: 850 | M18: 850 | N18: Giben do Brasil | O18: 1801
J19: SERVIÇO DE PINTURA / ANODIZAÇÃO DE OPERADOR / FOLHA | K19: 1.00 | L19: 790 | M19: 790 | N19: Nova Vidraçaria | O19: 1723
J20: SERVIÇO DE PINTURA / ANODIZAÇÃO DE OPERADOR / FOLHA | K20: 1.00 | L20: 790 | M20: 790 | N20: AD&N Consultoria | O20: 1732
... J53: SERVIÇO DE PINTURA / ANODIZAÇÃO DE OPERADOR / FOLHA | K53: 3.00 | L53: 430 | M53: 1290 | N53: SECOVIMED | O53: 1726

Sheet Configurador

Sheet NF-e NC
A1: OS | B1: CLIENTE | C1: TOTAL OS | D1: NF-e | E1: VALOR NF-e | F1: CFOP | G1: NATUREZA | H1: CHAVE | I1: EMISSÃO | J1: STATUS | K1: OBSERVAÇÕES | L1: PDF | M1: XML
A2: 115 | B2: Mondelez Brasil Ltda | C2: 28360.9 | D2: 5011 | E2: 22940.9 | F2: 5102 | G2: =VLOOKUP(F2,CFOP[],2,FALSE) -> Venda de mercadoria adquirida ou recebida de terceiros | H2: 41250313929397000142550010000050111000865610 | I2: 45740 | J2: Emitida | L2: OK | M2: OK
A3: 327 | B3: Renault do Brasil Ltda | C3: 6468.4 | D3: 5200 | E3: 2918.4 | F3: 5102 | G3: =VLOOKUP(F3,CFOP[],2,FALSE) -> Venda de mercadoria adquirida ou recebida de terceiros | H3: 41250813929397000142550010000052001928889133 | I3: 45870 | J3: Emitida | L3: OK | M3: OK
A4: 280 | B4: Graham Packaging do Brasil Indústria e Comércio Ltda | C4: 32138.53 | D4: 5248 | E4: 29138.53 | F4: 5101 | G4: =VLOOKUP(F4,CFOP[],2,FALSE) -> Venda de produção do estabelecimento | H4: 41250913929397000142550010000052481805589643 | I4: 45905 | J4: Emitida | L4: OK | M4: OK
A5: 390 | B5: Sig Combibloc do Brasil Ltda | C5: 3586.3 | D5: 5257 | E5: 1898.8 | F5: 5102 | G5: =VLOOKUP(F5,CFOP[],2,FALSE) -> Venda de mercadoria adquirida ou recebida de terceiros | H5: 41250913929397000142550010000052571482726007 | I5: 45916 | J5: Emitida | L5: OK | M5: OK
A6: 393 | B6: Sig Combibloc do Brasil Ltda | C6: 7558 | D6: 5292 | E6: 6038 | F6: 5102 | G6: =VLOOKUP(F6,CFOP[],2,FALSE) -> Venda de mercadoria adquirida ou recebida de terceiros | H6: 41251013929397000142550010000052921412199589 | I6: 45938 | J6: Emitida | L6: OK | M6: OK
A7: 446 | B7: Condomínio Edifício Residence Batel | C7: 178 | D7: 5301 | E7: 178 | F7: 5102 | G7: =VLOOKUP(F7,CFOP[],2,FALSE) -> Venda de mercadoria adquirida ou recebida de terceiros | H7: 41251013929397000142550010000053011287202517 | I7: 45945 | J7: Emitida
A8: 447 | B8: Sindicato Dos Empregados Em Estabelecimentos Bancários | C8: 190 | D8: 5302 | E8: 190 | F8: 5102 | G8: =VLOOKUP(F8,CFOP[],2,FALSE) -> Venda de mercadoria adquirida ou recebida de terceiros | H8: 41251013929397000142550010000053021287202514 | I8: 45945 | J8: Emitida
A9: - | B9: MetalFim Tratamentos de Superficie Ltda | C9: 6500 | D9: 5303 | E9: 6500 | F9: 5102 | G9: =VLOOKUP(F9,CFOP[],2,FALSE) -> Venda de mercadoria adquirida ou recebida de terceiros | H9: 41251013929397000142550010000053031287202511 | I9: 45945 | J9: Cancelada
A10: - | B10: MetalFim Tratamentos de Superficie Ltda | C10: 7800 | D10: 5304 | E10: 7800 | F10: 5901 | G10: =VLOOKUP(F10,CFOP[],2,FALSE) -> Remessa para industrialização por encomenda | H10: 41251013929397000142550010000053041287202519 | I10: 45945 | J10: Emitida
A11: 377 | B11: Netcom Construtora Ltda | C11: 1919.5 | D11: 5305 | E11: 1294.5 | F11: 5102 | G11: =VLOOKUP(F11,CFOP[],2,FALSE) -> Venda de mercadoria adquirida ou recebida de terceiros | H11: 41251013929397000142550010000053051295202511 | I11: 45953 | J11: Emitida
A12: 455 | B12: Luciana B G Der Bedrossian | C12: 908.7 | D12: 5306 | E12: 908.7 | F12: 5102 | G12: =VLOOKUP(F12,CFOP[],2,FALSE) -> Venda de mercadoria adquirida ou recebida de terceiros | H12: 41251013929397000142550010000053061287202513 | I12: 45945 | J12: Emitida
A13: 425 | B13: Mondelez Brasil Ltda | C13: 10600.47 | D13: 5307 | E13: 10600.47 | F13: 5102 | G13: =VLOOKUP(F13,CFOP[],2,FALSE) -> Venda de mercadoria adquirida ou recebida de terceiros | H13: 41251013929397000142550010000053071288202514 | I13: 45946 | J13: Emitida
A14: 410 | B14: Madeshopping Investimentos e Participações Ltda | C14: 9180 | D14: 5308 | E14: 4185 | F14: 5102 | G14: =VLOOKUP(F14,CFOP[],2,FALSE) -> Venda de mercadoria adquirida ou recebida de terceiros | H14: 41251013929397000142550010000053081288202511 | I14: 45946 | J14: Emitida
A15: 439 | B15: União Champagnat de Educação | C15: 1860 | D15: 5309 | E15: 970 | F15: 5102 | G15: =VLOOKUP(F15,CFOP[],2,FALSE) -> Venda de mercadoria adquirida ou recebida de terceiros | H15: 41251013929397000142550010000053091289202512 | I15: 45947 | J15: Emitida
A16: 456 | B16: Renault do Brasil Ltda | C16: 2524.2 | D16: 5310 | E16: 2374.2 | F16: 5102 | G16: =VLOOKUP(F16,CFOP[],2,FALSE) -> Venda de mercadoria adquirida ou recebida de terceiros | H16: 41251013929397000142550010000053101294202518 | I16: 45952 | J16: Cancelada
A17: - | B17: Calpie Pinturas Industriais Ltda | C17: 2150 | D17: 5311 | E17: 2150 | F17: 5901 | G17: =VLOOKUP(F17,CFOP[],2,FALSE) -> Remessa para industrialização por encomenda | H17: 41251013929397000142550010000053111292202518 | I17: 45950 | J17: Emitida
A18: 452 | B18: Ouro Verde Participações S/A | C18: 1186.5 | D18: 5312 | E18: 1186.5 | F18: 5102 | G18: =VLOOKUP(F18,CFOP[],2,FALSE) -> Venda de mercadoria adquirida ou recebida de terceiros | H18: 41251013929397000142550010000053121292202515 | I18: 45950 | J18: Emitida
A19: 457 | B19: Condomínio Edifício Residence Batel | C19: 1030.8 | D19: 5313 | E19: 1030.8 | F19: 5102 | G19: =VLOOKUP(F19,CFOP[],2,FALSE) -> Venda de mercadoria adquirida ou recebida de terceiros | H19: 41251013929397000142550010000053131293202516 | I19: 45951 | J19: Emitida
A20: 1157 | B20: Jockey Plaza Shopping Center | C20: 1613 | D20: 5314 | E20: 723 | F20: 5102 | G20: =VLOOKUP(F20,CFOP[],2,FALSE) -> Venda de mercadoria adquirida ou recebida de terceiros | H20: 41251013929397000142550010000053141293202513 | I20: 45951 | J20: Emitida
A21: 422 | B21: Pátio Batel Shopping Ltda | C21: 2098.65 | D21: 5315 | E21: 2098.65 | F21: 5102 | G21: =VLOOKUP(F21,CFOP[],2,FALSE) -> Venda de mercadoria adquirida ou recebida de terceiros | H21: 41251013929397000142550010000053151293202510 | I21: 45951 | J21: Emitida
A22: 1160 | B22: Parth Administração e Empreendimentos Ltda | C22: 894.9 | D22: 5316 | E22: 894.9 | F22: 5102 | G22: =VLOOKUP(F22,CFOP[],2,FALSE) -> Venda de mercadoria adquirida ou recebida de terceiros | H22: 41251013929397000142550010000053161293202518 | I22: 45951 | J22: Emitida
A23: 1117 | B23: HCL Hotéis Ltda | C23: 8614.9 | D23: 5317 | E23: 7454.9 | F23: 5102 | G23: =VLOOKUP(F23,CFOP[],2,FALSE) -> Venda de mercadoria adquirida ou recebida de terceiros | H23: 41251013929397000142550010000053171293202515 | I23: 45951 | J23: Emitida
A24: 440 | B24: Condomínio do Edifício Philadelphia | C24: 945 | D24: 5318 | E24: 945 | F24: 5102 | G24: =VLOOKUP(F24,CFOP[],2,FALSE) -> Venda de mercadoria adquirida ou recebida de terceiros | H24: 41251013929397000142550010000053181294202516 | I24: 45952 | J24: Emitida
A25: 407 | B25: Condomínio do Edifício Philadelphia | C25: 2980.8 | D25: 5319 | E25: 2980.8 | F25: 5102 | G25: =VLOOKUP(F25,CFOP[],2,FALSE) -> Venda de mercadoria adquirida ou recebida de terceiros | H25: 41251013929397000142550010000053191294202513 | I25: 45952 | J25: Emitida
A26: 441 | B26: Madero Industria e Comércio S.A | C26: 760 | D26: 5320 | E26: 510 | F26: 6102 | G26: =VLOOKUP(F26,CFOP[],2,FALSE) -> Venda de mercadoria adquirida ou recebida de terceiros | H26: 41251013929397000142550010000053201294202514 | I26: 45952 | J26: Emitida
A27: 378 | B27: Netcom Construtora Ltda | C27: 8486 | D27: 5321 | E27: 4036 | F27: 5102 | G27: =VLOOKUP(F27,CFOP[],2,FALSE) -> Venda de mercadoria adquirida ou recebida de terceiros | H27: 41251013929397000142550010000053211295202515 | I27: 45953 | J27: Emitida
A28: - | B28: MetalFim Tratamentos de Superficie Ltda | C28: 1540 | D28: 5322 | E28: 1540 | F28: 5901 | G28: =VLOOKUP(F28,CFOP[],2,FALSE) -> Remessa para industrialização por encomenda | H28: 41251013929397000142550010000053221295202512 | I28: 45953 | J28: Cancelada
A29: 456 | B29: Renault do Brasil Ltda | C29: 2524.2 | D29: 5323 | E29: 2524.2 | F29: 5102 | G29: =VLOOKUP(F29,CFOP[],2,FALSE) -> Venda de mercadoria adquirida ou recebida de terceiros | H29: 41251013929397000142550010000053231295202510 | I29: 45953 | J29: Emitida
A30: - | B30: Fast Pintura a Pó Ltda | C30: 1540 | D30: 5324 | E30: 1540 | F30: 5901 | G30: =VLOOKUP(F30,CFOP[],2,FALSE) -> Remessa para industrialização por encomenda | H30: 41251013929397000142550010000053241295202517 | I30: 45953 | J30: Emitida
A31: 451 | B31: Netcom Construtora Ltda | C31: 4785.2 | D31: 5325 | E31: 4785.2 | F31: 5102 | G31: =VLOOKUP(F31,CFOP[],2,FALSE) -> Venda de mercadoria adquirida ou recebida de terceiros | H31: 41251013929397000142550010000053251296202518 | I31: 45954 | J31: Cancelada
A32: 451 | B32: Netcom Construtora Ltda | C32: 4785.2 | D32: 5326 | E32: 4785.2 | F32: 5102 | G32: =VLOOKUP(F32,CFOP[],2,FALSE) -> Venda de mercadoria adquirida ou recebida de terceiros | H32: 41251013929397000142550010000053261296202515 | I32: 45954 | J32: Emitida
A33: 447 | B33: Sindicato Dos Empregados Em Estabelecimentos | C33: 790 | D33: 5327 | E33: 790 | F33: 5101 | G33: =VLOOKUP(F33,CFOP[],2,FALSE) -> Venda de produção do estabelecimento | H33: 41251013929397000142550010000053271300202518 | I33: 45958 | J33: Cancelada
A34: 365 | B34: Volkswagen do Brasil Industria de Veiculos Automotores Ltda | C34: 32346.3 | D34: 5328 | E34: 27131.3 | F34: 5102 | G34: =VLOOKUP(F34,CFOP[],2,FALSE) -> Venda de mercadoria adquirida ou recebida de terceiros | H34: 41251013929397000142550010000053281302202512 | I34: 45960 | J34: Emitida
A35: 427 | B35: Sig Combibloc do Brasil Ltda | C35: 5629 | D35: 5329 | E35: 3379 | F35: 5102 | G35: =VLOOKUP(F35,CFOP[],2,FALSE) -> Venda de mercadoria adquirida ou recebida de terceiros | H35: 41251013929397000142550010000053291302202510 | I35: 45960 | J35: Emitida
A36: 431 | B36: Sig Combibloc do Brasil Ltda | C36: 3842.6 | D36: 5330 | E36: 1722.6 | F36: 5102 | G36: =VLOOKUP(F36,CFOP[],2,FALSE) -> Venda de mercadoria adquirida ou recebida de terceiros | H36: 41251013929397000142550010000053301302202510 | I36: 45960 | J36: Emitida
A37: 1201 | B37: Memphis Engenharia e Serviços Ltda | C37: 1342.45 | D37: 5331 | E37: 1342.45 | F37: 5102 | G37: =VLOOKUP(F37,CFOP[],2,FALSE) -> Venda de mercadoria adquirida ou recebida de terceiros | H37: 41251013929397000142550010000053311302202518 | I37: 45960 | J37: Emitida
A38: 447 | B38: Sindicato Dos Empregados Em Estabelecimentos | C38: 790 | D38: 5332 | E38: 790 | F38: 5102 | G38: =VLOOKUP(F38,CFOP[],2,FALSE) -> Venda de mercadoria adquirida ou recebida de terceiros | H38: 41251013929397000142550010000053321303202519 | I38: 45961 | J38: Emitida
A39: 1189 | B39: Gusto & Henri Supermercados Ltda | C39: 2711.6 | D39: 5333 | E39: 1731.6 | F39: 5102 | G39: =VLOOKUP(F39,CFOP[],2,FALSE) -> Venda de mercadoria adquirida ou recebida de terceiros | H39: 41251013929397000142550010000053331303202516 | I39: 45961 | J39: Emitida
A40: 460 | B40: Hergen S/A Maquinas e Equipamentos | C40: 4806 | D40: 5334 | E40: 4806 | F40: 6102 | G40: =VLOOKUP(F40,CFOP[],2,FALSE) -> Venda de mercadoria adquirida ou recebida de terceiros | H40: 41251113929397000142550010000053341306202518 | I40: 45964 | J40: Emitida
A41: 1192 | B41: Filial 17 - Condor Super Center Ltda | C41: 3907.1 | D41: 5335 | E41: 3907.1 | F41: 5102 | G41: =VLOOKUP(F41,CFOP[],2,FALSE) -> Venda de mercadoria adquirida ou recebida de terceiros | H41: 41251113929397000142550010000053351307202519 | I41: 45965 | J41: Cancelada
A42: - | B42: Calpie Pinturas Industriais Ltda | C42: 6000 | D42: 5336 | E42: 6000 | F42: 5901 | G42: =VLOOKUP(F42,CFOP[],2,FALSE) -> Remessa para industrialização por encomenda | H42: 41251113929397000142550010000053361307202516 | I42: 45965 | J42: Emitida
A43: - | B43: Calpie Pinturas Industriais Ltda | C43: 2600 | D43: 5337 | E43: 2600 | F43: 5901 | G43: =VLOOKUP(F43,CFOP[],2,FALSE) -> Remessa para industrialização por encomenda | H43: 41251113929397000142550010000053371307202513 | I43: 45965 | J43: Emitida
A44: - | B44: Calpie Pinturas Industriais Ltda | C44: 2600 | D44: 5338 | E44: 2600 | F44: 5901 | G44: =VLOOKUP(F44,CFOP[],2,FALSE) -> Remessa para industrialização por encomenda | H44: 41251113929397000142550010000053381307202510 | I44: 45965 | J44: Emitida
A45: - | B45: Anosul Anodizadora de Alumínio Ltda | C45: 7580 | D45: 5339 | E45: 7580 | F45: 5901 | G45: =VLOOKUP(F45,CFOP[],2,FALSE) -> Remessa para industrialização por encomenda | H45: 41251113929397000142550010000053391307202518 | I45: 45965 | J45: Emitida
A46: - | B46: Calpie Pinturas Industriais Ltda | C46: 2600 | D46: 5340 | E46: 2600 | F46: 5901 | G46: =VLOOKUP(F46,CFOP[],2,FALSE) -> Remessa para industrialização por encomenda | H46: 41251113929397000142550010000053401307202519 | I46: 45965 | J46: Emitida
A47: - | B47: Calpie Pinturas Industriais Ltda | C47: 3400 | D47: 5341 | E47: 3400 | F47: 5901 | G47: =VLOOKUP(F47,CFOP[],2,FALSE) -> Remessa para industrialização por encomenda | H47: 41251113929397000142550010000053411307202516 | I47: 45965 | J47: Emitida
A48: 1192 | B48: Filial 17 - Condor Super Center Ltda | C48: 3907.1 | D48: 5342 | E48: 1566.5 | F48: 5102 | G48: =VLOOKUP(F48,CFOP[],2,FALSE) -> Venda de mercadoria adquirida ou recebida de terceiros | H48: 41251213929397000142550010000053421335202518 | I48: 45993 | J48: Emitida
A49: 1192 | B49: Filial 17 - Condor Super Center Ltda | C49: 3907.1 | D49: 5343 | E49: 2340.6 | F49: 5102 | G49: =VLOOKUP(F49,CFOP[],2,FALSE) -> Venda de mercadoria adquirida ou recebida de terceiros | H49: 41251113929397000142550010000053431308202514 | I49: 45966 | J49: Emitida
A50: 442 | B50: Mondelez Brasil Ltda | C50: 428.2 | D50: 5344 | E50: 428.2 | F50: 5102 | G50: =VLOOKUP(F50,CFOP[],2,FALSE) -> Venda de mercadoria adquirida ou recebida de terceiros | H50: 41251113929397000142550010000053441309202515 | I50: 45967 | J50: Emitida
A51: 238 | B51: Robert Bosch Limitada | C51: 7465 | D51: 5345 | E51: 7465 | F51: 5101 | G51: =VLOOKUP(F51,CFOP[],2,FALSE) -> Venda de produção do estabelecimento | H51: 41251113929397000142550010000053451310202512 | I51: 45968 | J51: Emitida
A52: 1123 | B52: Mondelez Brasil Ltda | C52: 29734.3 | D52: 5346 | E52: 23314.3 | F52: 5102 | G52: =VLOOKUP(F52,CFOP[],2,FALSE) -> Venda de mercadoria adquirida ou recebida de terceiros | H52: 41251113929397000142550010000053461313202510 | I52: 45971 | J52: Emitida
A53: 401 | B53: Mondelez Brasil Ltda | C53: 33341.4 | D53: 5347 | E53: 27681.4 | F53: 5102 | G53: =VLOOKUP(F53,CFOP[],2,FALSE) -> Venda de mercadoria adquirida ou recebida de terceiros | H53: 41251113929397000142550010000053471313202518 | I53: 45971 | J53: Emitida
A54: 1228 | B54: Filial 17 - Condor Super Center Ltda | C54: 6273.54 | D54: 5348 | E54: 6273.54 | F54: 5102 | G54: =VLOOKUP(F54,CFOP[],2,FALSE) -> Venda de mercadoria adquirida ou recebida de terceiros | H54: 41251113929397000142550010000053481313202515 | I54: 45971 | J54: Emitida
A55: 1227 | B55: Triermach Comercio e Servicos Ltda | C55: 1613 | D55: 5349 | E55: 723 | F55: 5102 | G55: =VLOOKUP(F55,CFOP[],2,FALSE) -> Venda de mercadoria adquirida ou recebida de terceiros | H55: 41251113929397000142550010000053491313202512 | I55: 45971 | J55: Emitida
A56: 1151 | B56: Slaviero Empreendimentos Hoteleiros Ltda | C56: 5053 | D56: 5350 | E56: 723 | F56: 5102 | G56: =VLOOKUP(F56,CFOP[],2,FALSE) -> Venda de mercadoria adquirida ou recebida de terceiros | H56: 41251113929397000142550010000053501316202514 | I56: 45974 | J56: Emitida
A57: 436 | B57: Renault do Brasil Ltda | C57: 5180 | D57: 5351 | E57: 3360 | F57: 5102 | G57: =VLOOKUP(F57,CFOP[],2,FALSE) -> Venda de mercadoria adquirida ou recebida de terceiros | H57: 41251113929397000142550010000053511320202512 | I57: 45978 | J57: Emitida
A58: 1242 | B58: Edimar Sobolevski | C58: 1320 | D58: 5352 | E58: 1100 | F58: 6102 | G58: =VLOOKUP(F58,CFOP[],2,FALSE) -> Venda de mercadoria adquirida ou recebida de terceiros | H58: 41251113929397000142550010000053521320202510 | I58: 45978 | J58: Emitida
A59: 1096 | B59: In Haus Industrial e Serviços de Logistica S/A | C59: 1588 | D59: 5353 | E59: 698 | F59: 5102 | G59: =VLOOKUP(F59,CFOP[],2,FALSE) -> Venda de mercadoria adquirida ou recebida de terceiros | H59: 41251113929397000142550010000053531320202517 | I59: 45978 | J59: Emitida
... A62: 461 | B62: Climasul Ar Condicionado Ltda | C62: 3367.3 | D62: 5356 | E62: 3367.3 | F62: 5102 | G62: =VLOOKUP(F62,CFOP[],2,FALSE) -> Venda de mercadoria adquirida ou recebida de terceiros | H62: 41251113929397000142550010000053561322202516 | I62: 45980 | J62: Emitida
A63: - | B63: Calpie Pinturas Industriais Ltda | C63: 7660 | D63: 5357 | E63: 7660 | F63: 5901 | G63: =VLOOKUP(F63,CFOP[],2,FALSE) -> Remessa para industrialização por encomenda | H63: 41251113929397000142550010000053571328202515 | I63: 45986 | J63: Emitida
A64: 1253 | B64: DVS Comércio de Veículos Ltda | C64: 4236 | D64: 5358 | E64: 4236 | F64: 5102 | G64: =VLOOKUP(F64,CFOP[],2,FALSE) -> Venda de mercadoria adquirida ou recebida de terceiros | H64: 41251113929397000142550010000053581327202519 | I64: 45985 | J64: Emitida
A65: 1145 | B65: Ebanx Ltda | C65: 16247.15 | D65: 5359 | E65: 6447.15 | F65: 5102 | G65: =VLOOKUP(F65,CFOP[],2,FALSE) -> Venda de mercadoria adquirida ou recebida de terceiros | H65: 41251113929397000142550010000053591327202516 | I65: 45985 | J65: Emitida
A66: 1251 | B66: Callfarma Comércio de Medicamentos Ltda | C66: 1720 | D66: 5360 | E66: 830 | F66: 5102 | G66: =VLOOKUP(F66,CFOP[],2,FALSE) -> Venda de mercadoria adquirida ou recebida de terceiros | H66: 41251113929397000142550010000053601327202517 | I66: 45985 | J66: Emitida
A67: - | B67: Calpie Pinturas Industriais Ltda | C67: 13900 | D67: 5361 | E67: 13900 | F67: 5901 | G67: =VLOOKUP(F67,CFOP[],2,FALSE) -> Remessa para industrialização por encomenda | H67: 41251113929397000142550010000053611328202518 | I67: 45986 | J67: Emitida
A68: - | B68: Calpie Pinturas Industriais Ltda | C68: 5910 | D68: 5362 | E68: 5910 | F68: 5901 | G68: =VLOOKUP(F68,CFOP[],2,FALSE) -> Remessa para industrialização por encomenda | H68: 41251113929397000142550010000053621328202515 | I68: 45986 | J68: Emitida
A69: - | B69: Calpie Pinturas Industriais Ltda | C69: 4520 | D69: 5363 | E69: 4520 | F69: 5901 | G69: =VLOOKUP(F69,CFOP[],2,FALSE) -> Remessa para industrialização por encomenda | H69: 41251113929397000142550010000053631328202512 | I69: 45986 | J69: Emitida
A70: - | B70: Tecnodock Comércio Industria Importação e Exportação Ltda | C70: 7560 | D70: 5364 | E70: 7560 | F70: 2202 | G70: =VLOOKUP(F70,CFOP[],2,FALSE) -> Devolução de venda de mercadoria adquirida ou recebida de terceiros | H70: 41251113929397000142550010000053641329202513 | I70: 45987 | J70: Cancelada
A71: 1271 | B71: Liga das Senhoras Católicas de Curitiba | C71: 1865.7 | D71: 5365 | E71: 1865.7 | F71: 5102 | G71: =VLOOKUP(F71,CFOP[],2,FALSE) -> Venda de mercadoria adquirida ou recebida de terceiros | H71: 41251113929397000142550010000053651330202510 | I71: 45988 | J71: Emitida
A72: 1241 | B72: Triermach Comercio e Servicos Ltda | C72: 5111.3 | D72: 5366 | E72: 5111.3 | F72: 5102 | G72: =VLOOKUP(F72,CFOP[],2,FALSE) -> Venda de mercadoria adquirida ou recebida de terceiros | H72: 41251113929397000142550010000053661330202518 | I72: 45988 | J72: Emitida
A73: 1277 | B73: Frimesa Cooperativa Central | C73: 3440 | D73: 5367 | E73: 3440 | F73: 5102 | G73: =VLOOKUP(F73,CFOP[],2,FALSE) -> Venda de mercadoria adquirida ou recebida de terceiros | H73: 41251113929397000142550010000053671330202515 | I73: 45988 | J73: Emitida
A74: 332 | B74: JJGC Industria e Comercio de Materiais Dentários S.A | C74: 33874.91 | D74: 5368 | E74: 28469.41 | F74: 5102 | G74: =VLOOKUP(F74,CFOP[],2,FALSE) -> Venda de mercadoria adquirida ou recebida de terceiros | H74: 41251113929397000142550010000053681331202516 | I74: 45989 | J74: Cancelada
A75: 1118 | B75: JJGC Industria e Comercio de Materiais Dentarios S.A | C75: 17644.3 | D75: 5369 | E75: 12901 | F75: 5102 | G75: =VLOOKUP(F75,CFOP[],2,FALSE) -> Venda de mercadoria adquirida ou recebida de terceiros | H75: 41251113929397000142550010000053691331202513 | I75: 45989 | J75: Emitida
A76: - | B76: Renault do Brasil Ltda | C76: 5000 | D76: 5370 | E76: 5000 | F76: 5916 | G76: =VLOOKUP(F76,CFOP[],2,FALSE) -> Retorno de mercadoria recebida para conserto ou reparo | H76: 41251113929397000142550010000053701331202514 | I76: 45989 | J76: Emitida
A77: 399 | B77: Renault do Brasil Ltda | C77: 7644.5 | D77: 5371 | E77: 1333.2 | F77: 5102 | G77: =VLOOKUP(F77,CFOP[],2,FALSE) -> Venda de mercadoria adquirida ou recebida de terceiros | H77: 41251113929397000142550010000053711331202511 | I77: 45989 | J77: Emitida
A78: 332 | B78: JJGC Industria e Comercio de Materiais Dentarios S.A | C78: 33874.81 | D78: 5372 | E78: 28469.41 | F78: 5102 | G78: =VLOOKUP(F78,CFOP[],2,FALSE) -> Venda de mercadoria adquirida ou recebida de terceiros | H78: 41251213929397000142550010000053721334202513 | I78: 45992 | J78: Emitida
A79: 1285 | B79: Filial 28 - Condor Super Center Ltda | C79: 5372.64 | D79: 5373 | E79: 5372.64 | F79: 5102 | G79: =VLOOKUP(F79,CFOP[],2,FALSE) -> Venda de mercadoria adquirida ou recebida de terceiros | H79: 41251213929397000142550010000053731334202510 | I79: 45992 | J79: Emitida
A80: 1284 | B80: Filial 01 - Condor Super Center Ltda | C80: 1315.7 | D80: 5374 | E80: 665.7 | F80: 5102 | G80: =VLOOKUP(F80,CFOP[],2,FALSE) -> Venda de mercadoria adquirida ou recebida de terceiros | H80: 41251213929397000142550010000053741334202518 | I80: 45992 | J80: Emitida
A81: - | B81: Tecnodock Comércio Industria Importação e Exportação Ltda | C81: 7560 | D81: 5375 | E81: 7560 | F81: 2202 | G81: =VLOOKUP(F81,CFOP[],2,FALSE) -> Devolução de venda de mercadoria adquirida ou recebida de terceiros | H81: 41251213929397000142550010000053751336202512 | I81: 45994 | J81: Cancelada
A82: 1272 | B82: L&F Vidros Ltda | C82: 6160 | D82: 5376 | E82: 1240 | F82: 5101 | G82: =VLOOKUP(F82,CFOP[],2,FALSE) -> Venda de produção do estabelecimento | H82: 41251213929397000142550010000053761336202510 | I82: 45994 | J82: Cancelada
A83: 418 | B83: L&F Vidros Ltda | C83: 7445 | D83: 5377 | E83: 1180 | F83: 5101 | G83: =VLOOKUP(F83,CFOP[],2,FALSE) -> Venda de produção do estabelecimento | H83: 41251213929397000142550010000053771336202517 | I83: 45994 | J83: Cancelada
A84: 1272 | B84: L&F Vidros Ltda | C84: 6160 | D84: 5378 | E84: 1240 | F84: 5101 | G84: =VLOOKUP(F84,CFOP[],2,FALSE) -> Venda de produção do estabelecimento | H84: 41251213929397000142550010000053781337202518 | I84: 45995 | J84: Emitida
A85: 418 | B85: L&F Vidros Ltda | C85: 7445 | D85: 5379 | E85: 1180 | F85: 5101 | G85: =VLOOKUP(F85,CFOP[],2,FALSE) -> Venda de produção do estabelecimento | H85: 41251213929397000142550010000053791337202515 | I85: 45995 | J85: Emitida
A86: - | B86: Rissi Fachadas e Esquadrias Ltda | C86: 16224.96 | D86: 5380 | E86: 16224.96 | F86: 6949 | G86: =VLOOKUP(F86,CFOP[],2,FALSE) -> Outra saída de mercadoria ou prestação de serviço não especificado | H86: 41251213929397000142550010000053801341202517 | I86: 45999 | J86: Emitida
A87: 983 | B87: Rissi Fachadas e Esquadrias Ltda | C87: 10685 | D87: 5381 | E87: 6205 | F87: 6102 | G87: =VLOOKUP(F87,CFOP[],2,FALSE) -> Venda de mercadoria adquirida ou recebida de terceiros | H87: 41251213929397000142550010000053811341202514 | I87: 45999 | J87: Emitida
A88: - | B88: Tecnodock Comércio Industria Importação e Exportação Ltda | C88: 7560 | D88: 5382 | E88: 7560 | F88: 6202 | G88: =VLOOKUP(F88,CFOP[],2,FALSE) -> Devolução de venda de mercadoria adquirida ou recebida de terceiros | H88: 41251213929397000142550010000053821341202511 | I88: 45999 | J88: Emitida
A89: 983 | B89: NB Engenharia Comercio e Construcoes Ltda | C89: 10685 | D89: 5383 | E89: 6205 | F89: 6108 | G89: =VLOOKUP(F89,CFOP[],2,FALSE) -> Venda de mercadoria adquirida ou recebida de terceiros, destinada a não contribuinte | H89: 41251213929397000142550010000053831342202512 | I89: 46000 | J89: Emitida
A90: 1260 | B90: 4L Serviços e Manutenções Ltda | C90: 2250 | D90: 5384 | E90: 2250 | F90: 5102 | G90: =VLOOKUP(F90,CFOP[],2,FALSE) -> Venda de mercadoria adquirida ou recebida de terceiros | H90: 41251213929397000142550010000053841343202513 | I90: 46001 | J90: Emitida
A91: 636 | B91: 4L Serviços e Manutenções Ltda | C91: 12523 | D91: 5385 | E91: 7443 | F91: 5102 | G91: =VLOOKUP(F91,CFOP[],2,FALSE) -> Venda de mercadoria adquirida ou recebida de terceiros | H91: 41251213929397000142550010000053851343202510 | I91: 46001 | J91: Emitida
A92: - | B92: Calpie Pinturas Industriais Ltda | C92: 2550 | D92: 5386 | E92: 2550 | F92: 5901 | G92: =VLOOKUP(F92,CFOP[],2,FALSE) -> Remessa para industrialização por encomenda | H92: 41251213929397000142550010000053861343202518 | I92: 46001 | J92: Emitida
A93: - | B93: Fast Pintura a Pó Ltda | C93: 627.6 | D93: 5387 | E93: 627.6 | F93: 5901 | G93: =VLOOKUP(F93,CFOP[],2,FALSE) -> Remessa para industrialização por encomenda | H93: 41251213929397000142550010000053871343202515 | I93: 46001 | J93: Emitida
A94: 1316 | B94: M . A. Rodrigues Goulart - Vidraçaria | C94: 1900 | D94: 5388 | E94: 1900 | F94: 5102 | G94: =VLOOKUP(F94,CFOP[],2,FALSE) -> Venda de mercadoria adquirida ou recebida de terceiros | H94: 41251213929397000142550010000053881344202516 | I94: 46002 | J94: Emitida
A95: 1225 | B95: M . A. Rodrigues Goulart - Vidracaria | C95: 5710.8 | D95: 5389 | E95: 380.8 | F95: 5102 | G95: =VLOOKUP(F95,CFOP[],2,FALSE) -> Venda de mercadoria adquirida ou recebida de terceiros | H95: 41251213929397000142550010000053891344202513 | I95: 46002 | J95: Emitida
A96: - | B96: Design Ferragens Ltda | C96: 3904.25 | D96: 5390 | E96: 3904.25 | F96: 5102 | G96: =VLOOKUP(F96,CFOP[],2,FALSE) -> Venda de mercadoria adquirida ou recebida de terceiros | H96: 41251213929397000142550010000053901345202518 | I96: 46003 | J96: Emitida
A97: 1158 | B97: Sumitomo Rubber do Brasil Ltda | C97: 14341.28 | D97: 5391 | E97: 14341.28 | F97: 5102 | G97: =VLOOKUP(F97,CFOP[],2,FALSE) -> Venda de mercadoria adquirida ou recebida de terceiros | H97: 41251213929397000142550010000053911345202515 | I97: 46003 | J97: Emitida
A98: 1341 | B98: Farmácia Irmãos Pavesi Ltda | C98: 778.5 | D98: 5392 | E98: 778.5 | F98: 5102 | G98: =VLOOKUP(F98,CFOP[],2,FALSE) -> Venda de mercadoria adquirida ou recebida de terceiros | H98: 41251213929397000142550010000053921349202517 | I98: 46007 | J98: Emitida
A99: 1343 | B99: JJGC Industria e Comercio de Materiais Dentarios S.A | C99: 9344.06 | D99: 5393 | E99: 8454.06 | F99: 5102 | G99: =VLOOKUP(F99,CFOP[],2,FALSE) -> Venda de mercadoria adquirida ou recebida de terceiros | H99: 41251213929397000142550010000053931350202514 | I99: 46008 | J99: Emitida
A100: 1342 | B100: Parth Administração e Empreendimentos Ltda | C100: 894.9 | D100: 5394 | E100: 894.9 | F100: 5102 | G100: =VLOOKUP(F100,CFOP[],2,FALSE) -> Venda de mercadoria adquirida ou recebida de terceiros | H100: 41251213929397000142550010000053941350202511 | I100: 46008 | J100: Emitida
A101: 1239 | B101: Mondelez Brasil Ltda | C101: 6461 | D101: 5395 | E101: 6461 | F101: 5102 | G101: =VLOOKUP(F101,CFOP[],2,FALSE) -> Venda de mercadoria adquirida ou recebida de terceiros | H101: 41251213929397000142550010000053951350202519 | I101: 46008 | J101: Emitida
A102: 1193 | B102: In Haus Industrial e Serviços de Logistica S/A | C102: 27710.5 | D102: 5396 | E102: 23420.5 | F102: 5102 | G102: =VLOOKUP(F102,CFOP[],2,FALSE) -> Venda de mercadoria adquirida ou recebida de terceiros | H102: 41251213929397000142550010000053961351202510 | I102: 46009 | J102: Emitida
...

Sheet NFS-e NC
A1: OS | B1: CLIENTE | C1: TOTAL OS | D1: NFS-e | E1: VALOR NFS-e | F1: DPS | G1: CHAVE | H1: DATA | I1: STATUS | J1: OBSERVAÇÕES | K1: RETER ISS | L1: ISS | M1: RETER INSS | N1: INSS | O1: VALOR LIQUIDO | P1: PDFs | Q1: XML
A2: 1218 | B2: Araúz & Advogados Associados | C2: 790 | D2: 1 | E2: 790 | F2: 1 | G2: 41069022213929397000142000000000000125117375775122 | H2: 45967 | I2: Emitida | K2: NÃO | L2: =_xlfn.IFS(NFSe_NC[[#This Row],[RETER ISS]]="NÃO",0,NFSe_NC[[#This Row],[RETER ISS]]="SIM",NFSe_NC[[#This Row],[VALOR NFS-e]]*5%) -> 0 | M2: NÃO | N2: {=_xlfn.IFS(NFSe_NC[[#This Row],[RETER INSS]]="NÃO",0,NFSe_NC[[#This Row],[RETER INSS]]="SIM",NFSe_NC[[#This Row],[VALOR NFS-e]]*11%)} -> 0 | O2: =E2-L2-N2 -> 790 | P2: OK | Q2: OK
A3: 1169 | B3: Condominio Palladium Shopping Center Curitiba | C3: 2560 | D3: 2 | E3: 2560 | F3: 22 | G3: 41069022213929397000142000000000000225118251173793 | H3: 45967 | I3: Cancelada | K3: NÃO | L3: =_xlfn.IFS(NFSe_NC[[#This Row],[RETER ISS]]="NÃO",0,NFSe_NC[[#This Row],[RETER ISS]]="SIM",NFSe_NC[[#This Row],[VALOR NFS-e]]*5%) -> 0 | M3: NÃO | N3: {=_xlfn.IFS(NFSe_NC[[#This Row],[RETER INSS]]="NÃO",0,NFSe_NC[[#This Row],[RETER INSS]]="SIM",NFSe_NC[[#This Row],[VALOR NFS-e]]*11%)} -> 0 | O3: =E3-L3-N3 -> 2560 | P3: OK | Q3: OK
A4: 425 | B4: Mondelez Brasil Ltda | C4: 14975.47 | D4: 3 | E4: 4375 | F4: 4 | G4: 41069022213929397000142000000000000325110788795272 | H4: 45968 | I4: Emitida | K4: NÃO | L4: =_xlfn.IFS(NFSe_NC[[#This Row],[RETER ISS]]="NÃO",0,NFSe_NC[[#This Row],[RETER ISS]]="SIM",NFSe_NC[[#This Row],[VALOR NFS-e]]*5%) -> 0 | M4: NÃO | N4: {=_xlfn.IFS(NFSe_NC[[#This Row],[RETER INSS]]="NÃO",0,NFSe_NC[[#This Row],[RETER INSS]]="SIM",NFSe_NC[[#This Row],[VALOR NFS-e]]*11%)} -> 0 | O4: =E4-L4-N4 -> 4375 | P4: OK | Q4: OK
A5: 1169 | B5: Condominio Palladium Shopping Center Curitiba | C5: 2560 | D5: 4 | E5: 2560 | F5: 21 | G5: 41069022213929397000142000000000000425111637155713 | H5: 45968 | I5: Emitida | K5: NÃO | L5: =_xlfn.IFS(NFSe_NC[[#This Row],[RETER ISS]]="NÃO",0,NFSe_NC[[#This Row],[RETER ISS]]="SIM",NFSe_NC[[#This Row],[VALOR NFS-e]]*5%) -> 0 | M5: NÃO | N5: {=_xlfn.IFS(NFSe_NC[[#This Row],[RETER INSS]]="NÃO",0,NFSe_NC[[#This Row],[RETER INSS]]="SIM",NFSe_NC[[#This Row],[VALOR NFS-e]]*11%)} -> 0 | O5: =E5-L5-N5 -> 2560 | P5: OK | Q5: OK
A6: 427 | B6: Sig Combibloc do Brasil Ltda | C6: 5629 | D6: 5 | E6: 2250 | F6: 15 | G6: 41069022213929397000142000000000000525118270293201 | H6: 45968 | I6: Emitida | K6: NÃO | L6: =_xlfn.IFS(NFSe_NC[[#This Row],[RETER ISS]]="NÃO",0,NFSe_NC[[#This Row],[RETER ISS]]="SIM",NFSe_NC[[#This Row],[VALOR NFS-e]]*5%) -> 0 | M6: NÃO | N6: {=_xlfn.IFS(NFSe_NC[[#This Row],[RETER INSS]]="NÃO",0,NFSe_NC[[#This Row],[RETER INSS]]="SIM",NFSe_NC[[#This Row],[VALOR NFS-e]]*11%)} -> 0 | O6: =E6-L6-N6 -> 2250 | P6: OK | Q6: OK
A7: 431 | B7: Sig Combibloc do Brasil Ltda | C7: 3842.6 | D7: 6 | E7: 2120 | F7: 18 | G7: 41069022213929397000142000000000000625111428150643 | H7: 45968 | I7: Emitida | K7: NÃO | L7: =_xlfn.IFS(NFSe_NC[[#This Row],[RETER ISS]]="NÃO",0,NFSe_NC[[#This Row],[RETER ISS]]="SIM",NFSe_NC[[#This Row],[VALOR NFS-e]]*5%) -> 0 | M7: NÃO | N7: {=_xlfn.IFS(NFSe_NC[[#This Row],[RETER INSS]]="NÃO",0,NFSe_NC[[#This Row],[RETER INSS]]="SIM",NFSe_NC[[#This Row],[VALOR NFS-e]]*11%)} -> 0 | O7: =E7-L7-N7 -> 2120 | P7: OK | Q7: OK
A8: 450 | B8: In Haus Industrial e Serviços de Logistica S/A | C8: 1280 | D8: 7 | E8: 1280 | F8: 13 | G8: 41069022213929397000142000000000000725115942115278 | H8: 45971 | I8: Emitida | K8: NÃO | L8: =_xlfn.IFS(NFSe_NC[[#This Row],[RETER ISS]]="NÃO",0,NFSe_NC[[#This Row],[RETER ISS]]="SIM",NFSe_NC[[#This Row],[VALOR NFS-e]]*5%) -> 0 | M8: NÃO | N8: {=_xlfn.IFS(NFSe_NC[[#This Row],[RETER INSS]]="NÃO",0,NFSe_NC[[#This Row],[RETER INSS]]="SIM",NFSe_NC[[#This Row],[VALOR NFS-e]]*11%)} -> 0 | O8: =E8-L8-N8 -> 1280 | P8: OK | Q8: OK
A9: 1227 | B9: Triermach Comércio e Serviços Ltda | C9: 1613 | D9: 8 | E9: 890 | F9: 24 | G9: 41069022213929397000142000000000000825110283723868 | H9: 45971 | I9: Emitida | K9: NÃO | L9: =_xlfn.IFS(NFSe_NC[[#This Row],[RETER ISS]]="NÃO",0,NFSe_NC[[#This Row],[RETER ISS]]="SIM",NFSe_NC[[#This Row],[VALOR NFS-e]]*5%) -> 0 | M9: NÃO | N9: {=_xlfn.IFS(NFSe_NC[[#This Row],[RETER INSS]]="NÃO",0,NFSe_NC[[#This Row],[RETER INSS]]="SIM",NFSe_NC[[#This Row],[VALOR NFS-e]]*11%)} -> 0 | O9: =E9-L9-N9 -> 890 | P9: OK | Q9: OK
A10: 390 | B10: Sig Combibloc do Brasil Ltda | C10: 3586.3 | D10: 9 | E10: 1687.5 | F10: 19 | G10: 41069022213929397000142000000000000925113078331188 | H10: 45971 | I10: Emitida | K10: NÃO | L10: =_xlfn.IFS(NFSe_NC[[#This Row],[RETER ISS]]="NÃO",0,NFSe_NC[[#This Row],[RETER ISS]]="SIM",NFSe_NC[[#This Row],[VALOR NFS-e]]*5%) -> 0 | M10: NÃO | N10: {=_xlfn.IFS(NFSe_NC[[#This Row],[RETER INSS]]="NÃO",0,NFSe_NC[[#This Row],[RETER INSS]]="SIM",NFSe_NC[[#This Row],[VALOR NFS-e]]*11%)} -> 0 | O10: =E10-L10-N10 -> 1687.5 | P10: OK | Q10: OK
A11: - | B11: Manusa do Brasil Comércio de Portas Automáticas Ltda | C11: 9579.43 | D11: 10 | E11: 9579.43 | F11: 25 | G11: 41069022213929397000142000000000001025116941085540 | H11: 45972 | I11: Cancelada | J11: Comissão | K11: NÃO | L11: =_xlfn.IFS(NFSe_NC[[#This Row],[RETER ISS]]="NÃO",0,NFSe_NC[[#This Row],[RETER ISS]]="SIM",NFSe_NC[[#This Row],[VALOR NFS-e]]*5%) -> 0 | M11: NÃO | N11: {=_xlfn.IFS(NFSe_NC[[#This Row],[RETER INSS]]="NÃO",0,NFSe_NC[[#This Row],[RETER INSS]]="SIM",NFSe_NC[[#This Row],[VALOR NFS-e]]*11%)} -> 0 | O11: =E11-L11-N11 -> 9579.43 | P11: OK | Q11: OK
A12: - | B12: Manusa do Brasil Comércio de Portas Automáticas Ltda | C12: 9579.43 | D12: 11 | E12: 9579.43 | F12: 26 | G12: 41069022213929397000142000000000001125117443559895 | H12: 45972 | I12: Emitida | J12: Comissão | K12: NÃO | L12: =_xlfn.IFS(NFSe_NC[[#This Row],[RETER ISS]]="NÃO",0,NFSe_NC[[#This Row],[RETER ISS]]="SIM",NFSe_NC[[#This Row],[VALOR NFS-e]]*5%) -> 0 | M12: NÃO | N12: {=_xlfn.IFS(NFSe_NC[[#This Row],[RETER INSS]]="NÃO",0,NFSe_NC[[#This Row],[RETER INSS]]="SIM",NFSe_NC[[#This Row],[VALOR NFS-e]]*11%)} -> 0 | O12: =E12-L12-N12 -> 9579.43 | P12: OK | Q12: OK
A13: 1096 | B13: In Haus Industrial e Serviços de Logistica S/A | C13: 1588 | D13: 12 | E13: 890 | F13: 27 | G13: 41069022213929397000142000000000001225117010358200 | H13: 45973 | I13: Emitida | K13: NÃO | L13: =_xlfn.IFS(NFSe_NC[[#This Row],[RETER ISS]]="NÃO",0,NFSe_NC[[#This Row],[RETER ISS]]="SIM",NFSe_NC[[#This Row],[VALOR NFS-e]]*5%) -> 0 | M13: NÃO | N13: {=_xlfn.IFS(NFSe_NC[[#This Row],[RETER INSS]]="NÃO",0,NFSe_NC[[#This Row],[RETER INSS]]="SIM",NFSe_NC[[#This Row],[VALOR NFS-e]]*11%)} -> 0 | O13: =E13-L13-N13 -> 890 | P13: OK | Q13: OK
A14: 115 | B14: Mondelez Brasil Ltda | C14: 5420 | D14: 13 | E14: 5420 | F14: 28 | G14: 41069022213929397000142000000000001325115679178519 | H14: 45973 | I14: Emitida | K14: NÃO | L14: =_xlfn.IFS(NFSe_NC[[#This Row],[RETER ISS]]="NÃO",0,NFSe_NC[[#This Row],[RETER ISS]]="SIM",NFSe_NC[[#This Row],[VALOR NFS-e]]*5%) -> 0 | M14: NÃO | N14: {=_xlfn.IFS(NFSe_NC[[#This Row],[RETER INSS]]="NÃO",0,NFSe_NC[[#This Row],[RETER INSS]]="SIM",NFSe_NC[[#This Row],[VALOR NFS-e]]*11%)} -> 0 | O14: =E14-L14-N14 -> 5420 | P14: OK | Q14: OK
A15: 317 | B15: Mondelez Brasil Ltda | C15: 1590 | D15: 14 | E15: 1590 | F15: 29 | G15: 41069022213929397000142000000000001425116388855460 | H15: 45973 | I15: Emitida | K15: NÃO | L15: =_xlfn.IFS(NFSe_NC[[#This Row],[RETER ISS]]="NÃO",0,NFSe_NC[[#This Row],[RETER ISS]]="SIM",NFSe_NC[[#This Row],[VALOR NFS-e]]*5%) -> 0 | M15: NÃO | N15: {=_xlfn.IFS(NFSe_NC[[#This Row],[RETER INSS]]="NÃO",0,NFSe_NC[[#This Row],[RETER INSS]]="SIM",NFSe_NC[[#This Row],[VALOR NFS-e]]*11%)} -> 0 | O15: =E15-L15-N15 -> 1590 | P15: OK | Q15: OK
A16: 365 | B16: Volkswagen do Brasil Industria de Veiculos Automotores Ltda | C16: 32346.3 | D16: 15 | E16: 4595 | F16: 7 | G16: 41069022213929397000142000000000001525117354140338 | H16: 45973 | I16: Cancelada | J16: Reemitida na OS #1276 | K16: SIM | L16: =_xlfn.IFS(NFSe_NC[[#This Row],[RETER ISS]]="NÃO",0,NFSe_NC[[#This Row],[RETER ISS]]="SIM",NFSe_NC[[#This Row],[VALOR NFS-e]]*5%) -> 229.75 | M16: NÃO | N16: {=_xlfn.IFS(NFSe_NC[[#This Row],[RETER INSS]]="NÃO",0,NFSe_NC[[#This Row],[RETER INSS]]="SIM",NFSe_NC[[#This Row],[VALOR NFS-e]]*11%)} -> 0 | O16: =E16-L16-N16 -> 4365.25 | P16: OK | Q16: OK
A17: 1151 | B17: Slaviero Empreendimentos Hoteleiros Ltda | C17: 5053 | D17: 16 | E17: 4330 | F17: 30 | G17: 41069022213929397000142000000000001625112163985832 | H17: 45974 | I17: Emitida | K17: NÃO | L17: =_xlfn.IFS(NFSe_NC[[#This Row],[RETER ISS]]="NÃO",0,NFSe_NC[[#This Row],[RETER ISS]]="SIM",NFSe_NC[[#This Row],[VALOR NFS-e]]*5%) -> 0 | M17: NÃO | N17: {=_xlfn.IFS(NFSe_NC[[#This Row],[RETER INSS]]="NÃO",0,NFSe_NC[[#This Row],[RETER INSS]]="SIM",NFSe_NC[[#This Row],[VALOR NFS-e]]*11%)} -> 0 | O17: =E17-L17-N17 -> 4330 | P17: OK | Q17: OK
A18: 401 | B18: Mondelez Brasil Ltda | C18: 33341.4 | D18: 17 | E18: 5660 | F18: 31 | G18: 41069022213929397000142000000000001725116555057780 | H18: 45974 | I18: Emitida | K18: NÃO | L18: =_xlfn.IFS(NFSe_NC[[#This Row],[RETER ISS]]="NÃO",0,NFSe_NC[[#This Row],[RETER ISS]]="SIM",NFSe_NC[[#This Row],[VALOR NFS-e]]*5%) -> 0 | M18: NÃO | N18: {=_xlfn.IFS(NFSe_NC[[#This Row],[RETER INSS]]="NÃO",0,NFSe_NC[[#This Row],[RETER INSS]]="SIM",NFSe_NC[[#This Row],[VALOR NFS-e]]*11%)} -> 0 | O18: =E18-L18-N18 -> 5660 | P18: OK | Q18: OK
A19: 1250 | B19: DVS Comércio de Veículos Ltda | C19: 890 | D19: 18 | E19: 890 | F19: 32 | G19: 41069022213929397000142000000000001825110120303986 | H19: 45979 | I19: Emitida | K19: NÃO | L19: =_xlfn.IFS(NFSe_NC[[#This Row],[RETER ISS]]="NÃO",0,NFSe_NC[[#This Row],[RETER ISS]]="SIM",NFSe_NC[[#This Row],[VALOR NFS-e]]*5%) -> 0 | M19: NÃO | N19: {=_xlfn.IFS(NFSe_NC[[#This Row],[RETER INSS]]="NÃO",0,NFSe_NC[[#This Row],[RETER INSS]]="SIM",NFSe_NC[[#This Row],[VALOR NFS-e]]*11%)} -> 0 | O19: =E19-L19-N19 -> 890 | P19: OK | Q19: OK
A20: 424 | B20: API SPE 46 - Planejamento e Desenvolvimento de Empr. Imob. | C20: 26180 | D20: 19 | E20: 15360 | F20: 33 | G20: 41069022213929397000142000000000001925119621385958 | H20: 45979 | I20: Emitida | J20: 1006/25 | K20: NÃO | L20: =_xlfn.IFS(NFSe_NC[[#This Row],[RETER ISS]]="NÃO",0,NFSe_NC[[#This Row],[RETER ISS]]="SIM",NFSe_NC[[#This Row],[VALOR NFS-e]]*5%) -> 0 | M20: NÃO | N20: {=_xlfn.IFS(NFSe_NC[[#This Row],[RETER INSS]]="NÃO",0,NFSe_NC[[#This Row],[RETER INSS]]="SIM",NFSe_NC[[#This Row],[VALOR NFS-e]]*11%)} -> 0 | O20: =E20-L20-N20 -> 15360 | P20: OK | Q20: OK
A21: 770 | B21: Gold Indústria e Comércio Ltda | C21: 10560 | D21: 20 | E21: 5100 | F21: 34 | G21: 41069022213929397000142000000000002025118467741801 | H21: 45980 | I21: Cancelada | K21: NÃO | L21: =_xlfn.IFS(NFSe_NC[[#This Row],[RETER ISS]]="NÃO",0,NFSe_NC[[#This Row],[RETER ISS]]="SIM",NFSe_NC[[#This Row],[VALOR NFS-e]]*5%) -> 0 | M21: NÃO | N21: {=_xlfn.IFS(NFSe_NC[[#This Row],[RETER INSS]]="NÃO",0,NFSe_NC[[#This Row],[RETER INSS]]="SIM",NFSe_NC[[#This Row],[VALOR NFS-e]]*11%)} -> 0 | O21: =E21-L21-N21 -> 5100 | P21: OK | Q21: OK
A22: 436 | B22: Renault do Brasil Ltda | C22: 5180 | D22: 21 | E22: 1820 | F22: 35 | G22: 41069022213929397000142000000000002125114966579148 | H22: 45980 | I22: Emitida | K22: NÃO | L22: =_xlfn.IFS(NFSe_NC[[#This Row],[RETER ISS]]="NÃO",0,NFSe_NC[[#This Row],[RETER ISS]]="SIM",NFSe_NC[[#This Row],[VALOR NFS-e]]*5%) -> 0 | M22: NÃO | N22: {=_xlfn.IFS(NFSe_NC[[#This Row],[RETER INSS]]="NÃO",0,NFSe_NC[[#This Row],[RETER INSS]]="SIM",NFSe_NC[[#This Row],[VALOR NFS-e]]*11%)} -> 0 | O22: =E22-L22-N22 -> 1820 | P22: OK | Q22: OK
A23: 1044 | B23: In Haus Industrial e Serviços de Logistica S/A | C23: 1126.76 | D23: 22 | E23: 1126.76 | F23: 36 | G23: 41069022213929397000142000000000002225115510460816 | H23: 45980 | I23: Emitida | K23: NÃO | L23: =_xlfn.IFS(NFSe_NC[[#This Row],[RETER ISS]]="NÃO",0,NFSe_NC[[#This Row],[RETER ISS]]="SIM",NFSe_NC[[#This Row],[VALOR NFS-e]]*5%) -> 0 | M23: NÃO | N23: {=_xlfn.IFS(NFSe_NC[[#This Row],[RETER INSS]]="NÃO",0,NFSe_NC[[#This Row],[RETER INSS]]="SIM",NFSe_NC[[#This Row],[VALOR NFS-e]]*11%)} -> 0 | O23: =E23-L23-N23 -> 1126.76 | P23: OK | Q23: OK
A24: 1185 | B24: In Haus Industrial e Serviços de Logistica S/A | C24: 1790 | D24: 23 | E24: 1790 | F24: 37 | G24: 41069022213929397000142000000000002325110338369340 | H24: 45980 | I24: Emitida | K24: NÃO | L24: =_xlfn.IFS(NFSe_NC[[#This Row],[RETER ISS]]="NÃO",0,NFSe_NC[[#This Row],[RETER ISS]]="SIM",NFSe_NC[[#This Row],[VALOR NFS-e]]*5%) -> 0 | M24: NÃO | N24: {=_xlfn.IFS(NFSe_NC[[#This Row],[RETER INSS]]="NÃO",0,NFSe_NC[[#This Row],[RETER INSS]]="SIM",NFSe_NC[[#This Row],[VALOR NFS-e]]*11%)} -> 0 | O24: =E24-L24-N24 -> 1790 | P24: OK | Q24: OK
A25: 1123 | B25: Mondelez Brasil Ltda | C25: 29734.3 | D25: 24 | E25: 6420 | F25: 38 | G25: 41069022213929397000142000000000002425110336852862 | H25: 45980 | I25: Emitida | K25: NÃO | L25: =_xlfn.IFS(NFSe_NC[[#This Row],[RETER ISS]]="NÃO",0,NFSe_NC[[#This Row],[RETER ISS]]="SIM",NFSe_NC[[#This Row],[VALOR NFS-e]]*5%) -> 0 | M25: NÃO | N25: {=_xlfn.IFS(NFSe_NC[[#This Row],[RETER INSS]]="NÃO",0,NFSe_NC[[#This Row],[RETER INSS]]="SIM",NFSe_NC[[#This Row],[VALOR NFS-e]]*11%)} -> 0 | O25: =E25-L25-N25 -> 6420 | P25: OK | Q25: OK
A26: 770 | B26: Gold Indústria e Comércio Ltda | C26: 10560 | D26: 25 | E26: 5100 | F26: 9 | G26: 41069022213929397000142000000000002525112114328296 | H26: 45982 | I26: Cancelada | K26: NÃO | L26: =_xlfn.IFS(NFSe_NC[[#This Row],[RETER ISS]]="NÃO",0,NFSe_NC[[#This Row],[RETER ISS]]="SIM",NFSe_NC[[#This Row],[VALOR NFS-e]]*5%) -> 0 | M26: NÃO | N26: {=_xlfn.IFS(NFSe_NC[[#This Row],[RETER INSS]]="NÃO",0,NFSe_NC[[#This Row],[RETER INSS]]="SIM",NFSe_NC[[#This Row],[VALOR NFS-e]]*11%)} -> 0 | O26: =E26-L26-N26 -> 5100 | P26: OK | Q26: OK
A27: 770 | B27: Gold Indústria e Comércio Ltda | C27: 10560 | D27: 26 | E27: 5100 | F27: 11 | G27: 41069022213929397000142000000000002625115450137440 | H27: 45982 | I27: Emitida | J27: Retenção ISS/INSS | K27: SIM | L27: =_xlfn.IFS(NFSe_NC[[#This Row],[RETER ISS]]="NÃO",0,NFSe_NC[[#This Row],[RETER ISS]]="SIM",NFSe_NC[[#This Row],[VALOR NFS-e]]*5%) -> 255 | M27: SIM | N27: {=_xlfn.IFS(NFSe_NC[[#This Row],[RETER INSS]]="NÃO",0,NFSe_NC[[#This Row],[RETER INSS]]="SIM",NFSe_NC[[#This Row],[VALOR NFS-e]]*11%)} -> 561 | O27: =E27-L27-N27 -> 4284 | P27: OK | Q27: OK
A28: 1259 | B28: Hospital Santa Cruz S/A | C28: 890 | D28: 27 | E28: 890 | F28: 39 | G28: 41069022213929397000142000000000002725117541231112 | H28: 45982 | I28: Cancelada | K28: NÃO | L28: =_xlfn.IFS(NFSe_NC[[#This Row],[RETER ISS]]="NÃO",0,NFSe_NC[[#This Row],[RETER ISS]]="SIM",NFSe_NC[[#This Row],[VALOR NFS-e]]*5%) -> 0 | M28: NÃO | N28: {=_xlfn.IFS(NFSe_NC[[#This Row],[RETER INSS]]="NÃO",0,NFSe_NC[[#This Row],[RETER INSS]]="SIM",NFSe_NC[[#This Row],[VALOR NFS-e]]*11%)} -> 0 | O28: =E28-L28-N28 -> 890 | P28: OK | Q28: OK
A29: 1263 | B29: Liga das Senhoras | C29: 890 | D29: 28 | E29: 890 | F29: 41 | G29: 41069022213929397000142000000000002825110054633963 | H29: 45985 | I29: Emitida | K29: NÃO | L29: =_xlfn.IFS(NFSe_NC[[#This Row],[RETER ISS]]="NÃO",0,NFSe_NC[[#This Row],[RETER ISS]]="SIM",NFSe_NC[[#This Row],[VALOR NFS-e]]*5%) -> 0 | M29: NÃO | N29: {=_xlfn.IFS(NFSe_NC[[#This Row],[RETER INSS]]="NÃO",0,NFSe_NC[[#This Row],[RETER INSS]]="SIM",NFSe_NC[[#This Row],[VALOR NFS-e]]*11%)} -> 0 | O29: =E29-L29-N29 -> 890 | P29: OK | Q29: OK
A30: 1145 | B30: Ebanx Ltda | C30: 16247.15 | D30: 29 | E30: 9800 | F30: 42 | G30: 41069022213929397000142000000000002925111848198190 | H30: 45985 | I30: Emitida | K30: NÃO | L30: =_xlfn.IFS(NFSe_NC[[#This Row],[RETER ISS]]="NÃO",0,NFSe_NC[[#This Row],[RETER ISS]]="SIM",NFSe_NC[[#This Row],[VALOR NFS-e]]*5%) -> 0 | M30: NÃO | N30: {=_xlfn.IFS(NFSe_NC[[#This Row],[RETER INSS]]="NÃO",0,NFSe_NC[[#This Row],[RETER INSS]]="SIM",NFSe_NC[[#This Row],[VALOR NFS-e]]*11%)} -> 0 | O30: =E30-L30-N30 -> 9800 | P30: OK | Q30: OK
A31: 1251 | B31: Callfarma Comércio de Medicamentos Ltda | C31: 1720 | D31: 30 | E31: 890 | F31: 43 | G31: 41069022213929397000142000000000003025110762653699 | H31: 45985 | I31: Emitida | K31: NÃO | L31: =_xlfn.IFS(NFSe_NC[[#This Row],[RETER ISS]]="NÃO",0,NFSe_NC[[#This Row],[RETER ISS]]="SIM",NFSe_NC[[#This Row],[VALOR NFS-e]]*5%) -> 0 | M31: NÃO | N31: {=_xlfn.IFS(NFSe_NC[[#This Row],[RETER INSS]]="NÃO",0,NFSe_NC[[#This Row],[RETER INSS]]="SIM",NFSe_NC[[#This Row],[VALOR NFS-e]]*11%)} -> 0 | O31: =E31-L31-N31 -> 890 | P31: OK | Q31: OK
A32: 1248 | B32: Hospital Union Ltda | C32: 980 | D32: 31 | E32: 980 | F32: 44 | G32: 41069022213929397000142000000000003125110071474581 | H32: 45985 | I32: Emitida | K32: NÃO | L32: =_xlfn.IFS(NFSe_NC[[#This Row],[RETER ISS]]="NÃO",0,NFSe_NC[[#This Row],[RETER ISS]]="SIM",NFSe_NC[[#This Row],[VALOR NFS-e]]*5%) -> 0 | M32: NÃO | N32: {=_xlfn.IFS(NFSe_NC[[#This Row],[RETER INSS]]="NÃO",0,NFSe_NC[[#This Row],[RETER INSS]]="SIM",NFSe_NC[[#This Row],[VALOR NFS-e]]*11%)} -> 0 | O32: =E32-L32-N32 -> 980 | P32: OK | Q32: OK
A33: 280 | B33: Graham Pack | C33: 32138.53 | D33: 32 | E33: 3000 | F33: 46 | G33: 41069022213929397000142000000000003225114199438898 | H33: 45987 | I33: Emitida | K33: NÃO | L33: =_xlfn.IFS(NFSe_NC[[#This Row],[RETER ISS]]="NÃO",0,NFSe_NC[[#This Row],[RETER ISS]]="SIM",NFSe_NC[[#This Row],[VALOR NFS-e]]*5%) -> 0 | M33: NÃO | N33: {=_xlfn.IFS(NFSe_NC[[#This Row],[RETER INSS]]="NÃO",0,NFSe_NC[[#This Row],[RETER INSS]]="SIM",NFSe_NC[[#This Row],[VALOR NFS-e]]*11%)} -> 0 | O33: =E33-L33-N33 -> 3000 | P33: OK | Q33: OK
A34: 1276 | B34: Volkswagen do Brasil Industria de Veiculos Automotores Ltda | C34: 32346.3 | D34: 33 | E34: 32346.3 | F34: 13 | G34: 41069022213929397000142000000000003325119683748322 | H34: 45987 | I34: Emitida | J34: Retenção ISS | K34: SIM | L34: =_xlfn.IFS(NFSe_NC[[#This Row],[RETER ISS]]="NÃO",0,NFSe_NC[[#This Row],[RETER ISS]]="SIM",NFSe_NC[[#This Row],[VALOR NFS-e]]*5%) -> 1617.315 | M34: NÃO | N34: {=_xlfn.IFS(NFSe_NC[[#This Row],[RETER INSS]]="NÃO",0,NFSe_NC[[#This Row],[RETER INSS]]="SIM",NFSe_NC[[#This Row],[VALOR NFS-e]]*11%)} -> 0 | O34: =E34-L34-N34 -> 30728.985 | P34: OK | Q34: OK
A35: - | B35: Manusa do Brasil Comércio de Portas Automáticas Ltda | C35: 9579.43 | D35: 34 | E35: 9579.43 | F35: 48 | G35: 41069022213929397000142000000000003425115012338300 | H35: 45988 | I35: Cancelada | J35: Comissão | K35: NÃO | L35: =_xlfn.IFS(NFSe_NC[[#This Row],[RETER ISS]]="NÃO",0,NFSe_NC[[#This Row],[RETER ISS]]="SIM",NFSe_NC[[#This Row],[VALOR NFS-e]]*5%) -> 0 | M35: NÃO | N35: {=_xlfn.IFS(NFSe_NC[[#This Row],[RETER INSS]]="NÃO",0,NFSe_NC[[#This Row],[RETER INSS]]="SIM",NFSe_NC[[#This Row],[VALOR NFS-e]]*11%)} -> 0 | O35: =E35-L35-N35 -> 9579.43 | P35: OK | Q35: OK
A36: - | B36: Manusa do Brasil Comércio de Portas Automáticas Ltda | C36: 20800.99 | D36: 35 | E36: 20800.99 | F36: 49 | G36: 41069022213929397000142000000000003525111147913761 | H36: 45988 | I36: Emitida | J36: Comissão | K36: NÃO | L36: =_xlfn.IFS(NFSe_NC[[#This Row],[RETER ISS]]="NÃO",0,NFSe_NC[[#This Row],[RETER ISS]]="SIM",NFSe_NC[[#This Row],[VALOR NFS-e]]*5%) -> 0 | M36: NÃO | N36: {=_xlfn.IFS(NFSe_NC[[#This Row],[RETER INSS]]="NÃO",0,NFSe_NC[[#This Row],[RETER INSS]]="SIM",NFSe_NC[[#This Row],[VALOR NFS-e]]*11%)} -> 0 | O36: =E36-L36-N36 -> 20800.99 | P36: OK | Q36: OK
A37: 1283 | B37: Filial 28 - Condor Super Center Ltda | C37: 920 | D37: 36 | E37: 920 | F37: 51 | G37: 41069022213929397000142000000000003625127767825850 | H37: 45992 | I37: Emitida | K37: NÃO | L37: =_xlfn.IFS(NFSe_NC[[#This Row],[RETER ISS]]="NÃO",0,NFSe_NC[[#This Row],[RETER ISS]]="SIM",NFSe_NC[[#This Row],[VALOR NFS-e]]*5%) -> 0 | M37: NÃO | N37: {=_xlfn.IFS(NFSe_NC[[#This Row],[RETER INSS]]="NÃO",0,NFSe_NC[[#This Row],[RETER INSS]]="SIM",NFSe_NC[[#This Row],[VALOR NFS-e]]*11%)} -> 0 | O37: =E37-L37-N37 -> 920 | P37: OK | Q37: OK
A38: 1284 | B38: Filial 01 - Condor Super Center Ltda | C38: 1315.7 | D38: 37 | E38: 650 | F38: 52 | G38: 41069022213929397000142000000000003725121359743937 | H38: 45992 | I38: Emitida | K38: NÃO | L38: =_xlfn.IFS(NFSe_NC[[#This Row],[RETER ISS]]="NÃO",0,NFSe_NC[[#This Row],[RETER ISS]]="SIM",NFSe_NC[[#This Row],[VALOR NFS-e]]*5%) -> 0 | M38: NÃO | N38: {=_xlfn.IFS(NFSe_NC[[#This Row],[RETER INSS]]="NÃO",0,NFSe_NC[[#This Row],[RETER INSS]]="SIM",NFSe_NC[[#This Row],[VALOR NFS-e]]*11%)} -> 0 | O38: =E38-L38-N38 -> 650 | P38: OK | Q38: OK
A39: 327 | B39: Renault do Brasil Ltda | C39: 6468.4 | D39: 38 | E39: 3550 | F39: 15 | G39: 41069022213929397000142000000000003825129068150343 | H39: 45992 | I39: Emitida | J39: Retenção ISS | K39: SIM | L39: =_xlfn.IFS(NFSe_NC[[#This Row],[RETER ISS]]="NÃO",0,NFSe_NC[[#This Row],[RETER ISS]]="SIM",NFSe_NC[[#This Row],[VALOR NFS-e]]*5%) -> 177.5 | M39: NÃO | N39: {=_xlfn.IFS(NFSe_NC[[#This Row],[RETER INSS]]="NÃO",0,NFSe_NC[[#This Row],[RETER INSS]]="SIM",NFSe_NC[[#This Row],[VALOR NFS-e]]*11%)} -> 0 | O39: =E39-L39-N39 -> 3372.5 | P39: OK | Q39: OK
A40: 976 | B40: Sig Combibloc do Brasil Ltda | C40: 1442.5 | D40: 39 | E40: 1442.5 | F40: 17 | G40: 41069022213929397000142000000000003925126737071427 | H40: 45992 | I40: Emitida | J40: Retenção ISS | K40: SIM | L40: =_xlfn.IFS(NFSe_NC[[#This Row],[RETER ISS]]="NÃO",0,NFSe_NC[[#This Row],[RETER ISS]]="SIM",NFSe_NC[[#This Row],[VALOR NFS-e]]*5%) -> 72.125 | M40: NÃO | N40: {=_xlfn.IFS(NFSe_NC[[#This Row],[RETER INSS]]="NÃO",0,NFSe_NC[[#This Row],[RETER INSS]]="SIM",NFSe_NC[[#This Row],[VALOR NFS-e]]*11%)} -> 0 | O40: =E40-L40-N40 -> 1370.375 | P40: OK | Q40: OK
A41: 399 | B41: Renault do Brasil Ltda | C41: 7644.5 | D41: 40 | E41: 6311.3 | F41: 19 | G41: 41069022213929397000142000000000004025121938531033 | H41: 45992 | I41: Emitida | J41: Retenção ISS | K41: SIM | L41: =_xlfn.IFS(NFSe_NC[[#This Row],[RETER ISS]]="NÃO",0,NFSe_NC[[#This Row],[RETER ISS]]="SIM",NFSe_NC[[#This Row],[VALOR NFS-e]]*5%) -> 315.565 | M41: NÃO | N41: {=_xlfn.IFS(NFSe_NC[[#This Row],[RETER INSS]]="NÃO",0,NFSe_NC[[#This Row],[RETER INSS]]="SIM",NFSe_NC[[#This Row],[VALOR NFS-e]]*11%)} -> 0 | O41: =E41-L41-N41 -> 5995.735 | P41: OK | Q41: OK
A42: 1259 | B42: Hospital Santa Cruz S/A | C42: 890 | D42: 41 | E42: 890 | F42: 53 | G42: 41069022213929397000142000000000004125120629247298 | H42: 45993 | I42: Emitida | K42: NÃO | L42: =_xlfn.IFS(NFSe_NC[[#This Row],[RETER ISS]]="NÃO",0,NFSe_NC[[#This Row],[RETER ISS]]="SIM",NFSe_NC[[#This Row],[VALOR NFS-e]]*5%) -> 0 | M42: NÃO | N42: {=_xlfn.IFS(NFSe_NC[[#This Row],[RETER INSS]]="NÃO",0,NFSe_NC[[#This Row],[RETER INSS]]="SIM",NFSe_NC[[#This Row],[VALOR NFS-e]]*11%)} -> 0 | O42: =E42-L42-N42 -> 890 | P42: OK | Q42: OK
A43: 1287 | B43: Edifício Centro Empresarial Glaser | C43: 890 | D43: 42 | E43: 890 | F43: 54 | G43: 41069022213929397000142000000000004225129169219498 | H43: 45994 | I43: Emitida | K43: NÃO | L43: =_xlfn.IFS(NFSe_NC[[#This Row],[RETER ISS]]="NÃO",0,NFSe_NC[[#This Row],[RETER ISS]]="SIM",NFSe_NC[[#This Row],[VALOR NFS-e]]*5%) -> 0 | M43: NÃO | N43: {=_xlfn.IFS(NFSe_NC[[#This Row],[RETER INSS]]="NÃO",0,NFSe_NC[[#This Row],[RETER INSS]]="SIM",NFSe_NC[[#This Row],[VALOR NFS-e]]*11%)} -> 0 | O43: =E43-L43-N43 -> 890 | P43: OK | Q43: OK
A44: 1272 | B44: L&F Vidros Ltda | C44: 6160 | D44: 43 | E44: 4920 | F44: 55 | G44: 41069022213929397000142000000000004325120505189242 | H44: 45994 | I44: Cancelada | K44: NÃO | L44: =_xlfn.IFS(NFSe_NC[[#This Row],[RETER ISS]]="NÃO",0,NFSe_NC[[#This Row],[RETER ISS]]="SIM",NFSe_NC[[#This Row],[VALOR NFS-e]]*5%) -> 0 | M44: NÃO | N44: {=_xlfn.IFS(NFSe_NC[[#This Row],[RETER INSS]]="NÃO",0,NFSe_NC[[#This Row],[RETER INSS]]="SIM",NFSe_NC[[#This Row],[VALOR NFS-e]]*11%)} -> 0 | O44: =E44-L44-N44 -> 4920 | P44: OK | Q44: OK
A45: 418 | B45: L&F Vidros Ltda | C45: 7445 | D45: 44 | E45: 6265 | F45: 56 | G45: 41069022213929397000142000000000004425122554185875 | H45: 45994 | I45: Cancelada | K45: NÃO | L45: =_xlfn.IFS(NFSe_NC[[#This Row],[RETER ISS]]="NÃO",0,NFSe_NC[[#This Row],[RETER ISS]]="SIM",NFSe_NC[[#This Row],[VALOR NFS-e]]*5%) -> 0 | M45: NÃO | N45: {=_xlfn.IFS(NFSe_NC[[#This Row],[RETER INSS]]="NÃO",0,NFSe_NC[[#This Row],[RETER INSS]]="SIM",NFSe_NC[[#This Row],[VALOR NFS-e]]*11%)} -> 0 | O45: =E45-L45-N45 -> 6265 | P45: OK | Q45: OK
A46: 1272 | B46: L&F Vidros Ltda | C46: 6160 | D46: 45 | E46: 4920 | F46: 21 | G46: 41069022213929397000142000000000004525127366785458 | H46: 45995 | I46: Cancelada | J46: Retenção ISS | K46: SIM | L46: =_xlfn.IFS(NFSe_NC[[#This Row],[RETER ISS]]="NÃO",0,NFSe_NC[[#This Row],[RETER ISS]]="SIM",NFSe_NC[[#This Row],[VALOR NFS-e]]*5%) -> 246 | M46: NÃO | N46: {=_xlfn.IFS(NFSe_NC[[#This Row],[RETER INSS]]="NÃO",0,NFSe_NC[[#This Row],[RETER INSS]]="SIM",NFSe_NC[[#This Row],[VALOR NFS-e]]*11%)} -> 0 | O46: =E46-L46-N46 -> 4674 | P46: OK | Q46: OK
A47: 418 | B47: L&F Vidros Ltda | C47: 7445 | D47: 46 | E47: 6265 | F47: 23 | G47: 41069022213929397000142000000000004625123779657605 | H47: 45995 | I47: Cancelada | J47: Retenção ISS | K47: SIM | L47: =_xlfn.IFS(NFSe_NC[[#This Row],[RETER ISS]]="NÃO",0,NFSe_NC[[#This Row],[RETER ISS]]="SIM",NFSe_NC[[#This Row],[VALOR NFS-e]]*5%) -> 313.25 | M47: NÃO | N47: {=_xlfn.IFS(NFSe_NC[[#This Row],[RETER INSS]]="NÃO",0,NFSe_NC[[#This Row],[RETER INSS]]="SIM",NFSe_NC[[#This Row],[VALOR NFS-e]]*11%)} -> 0 | O47: =E47-L47-N47 -> 5951.75 | P47: OK | Q47: OK
A48: 1269 | B48: JJGC Industria e Comercio de Materiais Dentarios S.A | C48: 890 | D48: 47 | E48: 890 | F48: 57 | G48: 41069022213929397000142000000000004725128256018270 | H48: 45995 | I48: Emitida | K48: NÃO | L48: =_xlfn.IFS(NFSe_NC[[#This Row],[RETER ISS]]="NÃO",0,NFSe_NC[[#This Row],[RETER ISS]]="SIM",NFSe_NC[[#This Row],[VALOR NFS-e]]*5%) -> 0 | M48: NÃO | N48: {=_xlfn.IFS(NFSe_NC[[#This Row],[RETER INSS]]="NÃO",0,NFSe_NC[[#This Row],[RETER INSS]]="SIM",NFSe_NC[[#This Row],[VALOR NFS-e]]*11%)} -> 0 | O48: =E48-L48-N48 -> 890 | P48: OK | Q48: OK
A49: 332 | B49: JJGC Industria e Comercio de Materiais Dentarios S.A | C49: 33874.91 | D49: 48 | E49: 5405.5 | F49: 50 | G49: 41069022213929397000142000000000004825120177152559 | H49: 45999 | I49: Cancelada | K49: NÃO | L49: =_xlfn.IFS(NFSe_NC[[#This Row],[RETER ISS]]="NÃO",0,NFSe_NC[[#This Row],[RETER ISS]]="SIM",NFSe_NC[[#This Row],[VALOR NFS-e]]*5%) -> 0 | M49: NÃO | N49: {=_xlfn.IFS(NFSe_NC[[#This Row],[RETER INSS]]="NÃO",0,NFSe_NC[[#This Row],[RETER INSS]]="SIM",NFSe_NC[[#This Row],[VALOR NFS-e]]*11%)} -> 0 | O49: =E49-L49-N49 -> 5405.5 | P49: OK | Q49: OK
A50: 332 | B50: JJGC Industria e Comercio de Materiais Dentarios S.A | C50: 33874.91 | D50: 49 | E50: 5405.5 | F50: 58 | G50: 41069022213929397000142000000000004925129989167841 | H50: 45999 | I50: Emitida | K50: NÃO | L50: =_xlfn.IFS(NFSe_NC[[#This Row],[RETER ISS]]="NÃO",0,NFSe_NC[[#This Row],[RETER ISS]]="SIM",NFSe_NC[[#This Row],[VALOR NFS-e]]*5%) -> 0 | M50: NÃO | N50: {=_xlfn.IFS(NFSe_NC[[#This Row],[RETER INSS]]="NÃO",0,NFSe_NC[[#This Row],[RETER INSS]]="SIM",NFSe_NC[[#This Row],[VALOR NFS-e]]*11%)} -> 0 | O50: =E50-L50-N50 -> 5405.5 | P50: OK | Q50: OK
A51: 1118 | B51: JJGC Industria e Comercio de Materiais Dentarios S.A | C51: 17644.3 | D51: 50 | E51: 4743.3 | F51: 59 | G51: 41069022213929397000142000000000005025125428494794 | H51: 45999 | I51: Emitida | K51: NÃO | L51: =_xlfn.IFS(NFSe_NC[[#This Row],[RETER ISS]]="NÃO",0,NFSe_NC[[#This Row],[RETER ISS]]="SIM",NFSe_NC[[#This Row],[VALOR NFS-e]]*5%) -> 0 | M51: NÃO | N51: {=_xlfn.IFS(NFSe_NC[[#This Row],[RETER INSS]]="NÃO",0,NFSe_NC[[#This Row],[RETER INSS]]="SIM",NFSe_NC[[#This Row],[VALOR NFS-e]]*11%)} -> 0 | O51: =E51-L51-N51 -> 4743.3 | P51: OK | Q51: OK
A52: 1272 | B52: L&F Vidros Ltda | C52: 6160 | D52: 51 | E52: 4920 | F52: 25 | G52: 41069022213929397000142000000000005125120256888750 | H52: 45999 | I52: Emitida | J52: Retenção ISS/INSS | K52: SIM | L52: =_xlfn.IFS(NFSe_NC[[#This Row],[RETER ISS]]="NÃO",0,NFSe_NC[[#This Row],[RETER ISS]]="SIM",NFSe_NC[[#This Row],[VALOR NFS-e]]*5%) -> 246 | M52: SIM | N52: {=_xlfn.IFS(NFSe_NC[[#This Row],[RETER INSS]]="NÃO",0,NFSe_NC[[#This Row],[RETER INSS]]="SIM",NFSe_NC[[#This Row],[VALOR NFS-e]]*11%)} -> 541.2 | O52: =E52-L52-N52 -> 4132.8 | P52: OK | Q52: OK
A53: 418 | B53: L&F Vidros Ltda | C53: 7445 | D53: 52 | E53: 6265 | F53: 27 | G53: 41069022213929397000142000000000005225124463168996 | H53: 45999 | I53: Emitida | J53: Retenção ISS/INSS | K53: SIM | L53: =_xlfn.IFS(NFSe_NC[[#This Row],[RETER ISS]]="NÃO",0,NFSe_NC[[#This Row],[RETER ISS]]="SIM",NFSe_NC[[#This Row],[VALOR NFS-e]]*5%) -> 313.25 | M53: SIM | N53: {=_xlfn.IFS(NFSe_NC[[#This Row],[RETER INSS]]="NÃO",0,NFSe_NC[[#This Row],[RETER INSS]]="SIM",NFSe_NC[[#This Row],[VALOR NFS-e]]*11%)} -> 689.15 | O53: =E53-L53-N53 -> 5262.6 | P53: OK | Q53: OK
A54: 636 | B54: 4L Serviços e Manutenções Ltda | C54: 12523 | D54: 53 | E54: 5080 | F54: 60 | G54: 41069022213929397000142000000000005325120177357422 | H54: 46001 | I54: Emitida | K54: NÃO | L54: =_xlfn.IFS(NFSe_NC[[#This Row],[RETER ISS]]="NÃO",0,NFSe_NC[[#This Row],[RETER ISS]]="SIM",NFSe_NC[[#This Row],[VALOR NFS-e]]*5%) -> 0 | M54: NÃO | N54: {=_xlfn.IFS(NFSe_NC[[#This Row],[RETER INSS]]="NÃO",0,NFSe_NC[[#This Row],[RETER INSS]]="SIM",NFSe_NC[[#This Row],[VALOR NFS-e]]*11%)} -> 0 | O54: =E54-L54-N54 -> 5080 | P54: OK | Q54: OK
A55: 1291 | B55: Hospital Santa Cruz S/A | C55: 890 | D55: 54 | E55: 890 | F55: 61 | G55: 41069022213929397000142000000000005425120017129492 | H55: 46001 | I55: Emitida | K55: NÃO | L55: =_xlfn.IFS(NFSe_NC[[#This Row],[RETER ISS]]="NÃO",0,NFSe_NC[[#This Row],[RETER ISS]]="SIM",NFSe_NC[[#This Row],[VALOR NFS-e]]*5%) -> 0 | M55: NÃO | N55: {=_xlfn.IFS(NFSe_NC[[#This Row],[RETER INSS]]="NÃO",0,NFSe_NC[[#This Row],[RETER INSS]]="SIM",NFSe_NC[[#This Row],[VALOR NFS-e]]*11%)} -> 0 | O55: =E55-L55-N55 -> 890 | P55: OK | Q55: OK
A56: 1225 | B56: M.A. Rodrigues Goulart - Vidraçaria | C56: 5710.8 | D56: 55 | E56: 5330 | F56: 29 | G56: 41069022213929397000142000000000005525129314576768 | H56: 46002 | I56: Emitida | J56: Retenção ISS | K56: SIM | L56: =_xlfn.IFS(NFSe_NC[[#This Row],[RETER ISS]]="NÃO",0,NFSe_NC[[#This Row],[RETER ISS]]="SIM",NFSe_NC[[#This Row],[VALOR NFS-e]]*5%) -> 266.5 | M56: NÃO | N56: {=_xlfn.IFS(NFSe_NC[[#This Row],[RETER INSS]]="NÃO",0,NFSe_NC[[#This Row],[RETER INSS]]="SIM",NFSe_NC[[#This Row],[VALOR NFS-e]]*11%)} -> 0 | O56: =E56-L56-N56 -> 5063.5 | P56: OK | Q56: OK
A57: 1326 | B57: Farmácia Irmãos Pavesi Ltda | C57: 890 | D57: 56 | E57: 890 | F57: 63 | G57: 41069022213929397000142000000000005625127567135732 | H57: 46003 | I57: Emitida | K57: NÃO | L57: =_xlfn.IFS(NFSe_NC[[#This Row],[RETER ISS]]="NÃO",0,NFSe_NC[[#This Row],[RETER ISS]]="SIM",NFSe_NC[[#This Row],[VALOR NFS-e]]*5%) -> 0 | M57: NÃO | N57: {=_xlfn.IFS(NFSe_NC[[#This Row],[RETER INSS]]="NÃO",0,NFSe_NC[[#This Row],[RETER INSS]]="SIM",NFSe_NC[[#This Row],[VALOR NFS-e]]*11%)} -> 0 | O57: =E57-L57-N57 -> 890 | P57: OK | Q57: OK
A58: 983 | B58: NB Engenharia Comércio e Construções Ltda | C58: 10685 | D58: 57 | E58: 4480 | F58: 31 | G58: 41069022213929397000142000000000005725120551396368 | H58: 46008 | I58: Emitida | J58: Retenção ISS/INSS | K58: SIM | L58: =_xlfn.IFS(NFSe_NC[[#This Row],[RETER ISS]]="NÃO",0,NFSe_NC[[#This Row],[RETER ISS]]="SIM",NFSe_NC[[#This Row],[VALOR NFS-e]]*5%) -> 224 | M58: SIM | N58: {=_xlfn.IFS(NFSe_NC[[#This Row],[RETER INSS]]="NÃO",0,NFSe_NC[[#This Row],[RETER INSS]]="SIM",NFSe_NC[[#This Row],[VALOR NFS-e]]*11%)} -> 492.8 | O58: =E58-L58-N58 -> 3763.2 | P58: OK | Q58: OK
A59: 393 | B59: Sig Combibloc do Brasil Ltda | C59: 7558 | D59: 58 | E59: 1520 | F59: 33 | G59: 41069022213929397000142000000000005825122167541675 | H59: 46008 | I59: Emitida | J59: Retenção ISS | K59: SIM | L59: =_xlfn.IFS(NFSe_NC[[#This Row],[RETER ISS]]="NÃO",0,NFSe_NC[[#This Row],[RETER ISS]]="SIM",NFSe_NC[[#This Row],[VALOR NFS-e]]*5%) -> 76 | M59: NÃO | N59: {=_xlfn.IFS(NFSe_NC[[#This Row],[RETER INSS]]="NÃO",0,NFSe_NC[[#This Row],[RETER INSS]]="SIM",NFSe_NC[[#This Row],[VALOR NFS-e]]*11%)} -> 0 | O59: =E59-L59-N59 -> 1444 | P59: OK | Q59: OK
A60: 1343 | B60: JJGC Industria e Comercio de Materiais Dentarios S.A | C60: 9344.06 | D60: 59 | E60: 890 | F60: 64 | G60: 41069022213929397000142000000000005925128350456684 | H60: 46008 | I60: Emitida | K60: NÃO | L60: =_xlfn.IFS(NFSe_NC[[#This Row],[RETER ISS]]="NÃO",0,NFSe_NC[[#This Row],[RETER ISS]]="SIM",NFSe_NC[[#This Row],[VALOR NFS-e]]*5%) -> 0 | M60: NÃO | N60: {=_xlfn.IFS(NFSe_NC[[#This Row],[RETER INSS]]="NÃO",0,NFSe_NC[[#This Row],[RETER INSS]]="SIM",NFSe_NC[[#This Row],[VALOR NFS-e]]*11%)} -> 0 | O60: =E60-L60-N60 -> 890 | P60: OK | Q60: OK
A61: 1340 | B61: Lightera Latam S.A | C61: 890 | D61: 60 | E61: 890 | F61: 65 | G61: 41069022213929397000142000000000006025128192258070 | H61: 46009 | I61: Cancelada | K61: NÃO | L61: =_xlfn.IFS(NFSe_NC[[#This Row],[RETER ISS]]="NÃO",0,NFSe_NC[[#This Row],[RETER ISS]]="SIM",NFSe_NC[[#This Row],[VALOR NFS-e]]*5%) -> 0 | M61: NÃO | N61: {=_xlfn.IFS(NFSe_NC[[#This Row],[RETER INSS]]="NÃO",0,NFSe_NC[[#This Row],[RETER INSS]]="SIM",NFSe_NC[[#This Row],[VALOR NFS-e]]*11%)} -> 0 | O61: =E61-L61-N61 -> 890 | P61: OK | Q61: OK
A62: 1328 | B62: Fundo Especial da Procuradoria Geral do Estado do Paraná - FEPGE/PR | C62: 2930 | D62: 61 | E62: 2930 | F62: 66 | G62: 41069022213929397000142000000000006125127618118826 | H62: 46009 | I62: Cancelada | K62: NÃO | L62: =_xlfn.IFS(NFSe_NC[[#This Row],[RETER ISS]]="NÃO",0,NFSe_NC[[#This Row],[RETER ISS]]="SIM",NFSe_NC[[#This Row],[VALOR NFS-e]]*5%) -> 0 | M62: NÃO | N62: {=_xlfn.IFS(NFSe_NC[[#This Row],[RETER INSS]]="NÃO",0,NFSe_NC[[#This Row],[RETER INSS]]="SIM",NFSe_NC[[#This Row],[VALOR NFS-e]]*11%)} -> 0 | O62: =E62-L62-N62 -> 2930 | P62: OK | Q62: OK
A63: 1328 | B63: Fundo Especial da Procuradoria Geral do Estado do Paraná - FEPGE/PR | C63: 2930 | D63: 62 | E63: 2930 | F63: 37 | G63: 41069022213929397000142000000000006225129691892412 | H63: 46009 | I63: Substituida | K63: NÃO | L63: =_xlfn.IFS(NFSe_NC[[#This Row],[RETER ISS]]="NÃO",0,NFSe_NC[[#This Row],[RETER ISS]]="SIM",NFSe_NC[[#This Row],[VALOR NFS-e]]*5%) -> 0 | M63: NÃO | N63: {=_xlfn.IFS(NFSe_NC[[#This Row],[RETER INSS]]="NÃO",0,NFSe_NC[[#This Row],[RETER INSS]]="SIM",NFSe_NC[[#This Row],[VALOR NFS-e]]*11%)} -> 0 | O63: =E63-L63-N63 -> 2930 | P63: OK | Q63: OK
A64: 1352 | B64: Hdez Empreendimentos Ltda | C64: 1540 | D64: 63 | E64: 950 | F64: 68 | G64: 41069022213929397000142000000000006325120522417342 | H64: 46009 | I64: Emitida | K64: NÃO | L64: =_xlfn.IFS(NFSe_NC[[#This Row],[RETER ISS]]="NÃO",0,NFSe_NC[[#This Row],[RETER ISS]]="SIM",NFSe_NC[[#This Row],[VALOR NFS-e]]*5%) -> 0 | M64: NÃO | N64: {=_xlfn.IFS(NFSe_NC[[#This Row],[RETER INSS]]="NÃO",0,NFSe_NC[[#This Row],[RETER INSS]]="SIM",NFSe_NC[[#This Row],[VALOR NFS-e]]*11%)} -> 0 | O64: =E64-L64-N64 -> 950 | P64: OK | Q64: OK
A65: 1172 | B65: Cia Beal de Alimentos | C65: 1945 | D65: 64 | E65: 950 | F65: 69 | G65: 41069022213929397000142000000000006425128149677401 | H65: 46010 | I65: Emitida | K65: NÃO | L65: =_xlfn.IFS(NFSe_NC[[#This Row],[RETER ISS]]="NÃO",0,NFSe_NC[[#This Row],[RETER ISS]]="SIM",NFSe_NC[[#This Row],[VALOR NFS-e]]*5%) -> 0 | M65: NÃO | N65: {=_xlfn.IFS(NFSe_NC[[#This Row],[RETER INSS]]="NÃO",0,NFSe_NC[[#This Row],[RETER INSS]]="SIM",NFSe_NC[[#This Row],[VALOR NFS-e]]*11%)} -> 0 | O65: =E65-L65-N65 -> 950 | P65: OK | Q65: OK
A66: 1293 | B66: Associação Franciscana de Ensino Senhor Bom Jesus | C66: 1068 | D66: 65 | E66: 890 | F66: 39 | G66: 41069022213929397000142000000000006525127614096253 | H66: 46010 | I66: Emitida | J66: Retenção ISS/INSS | K66: SIM | L66: =_xlfn.IFS(NFSe_NC[[#This Row],[RETER ISS]]="NÃO",0,NFSe_NC[[#This Row],[RETER ISS]]="SIM",NFSe_NC[[#This Row],[VALOR NFS-e]]*5%) -> 44.5 | M66: SIM | N66: {=_xlfn.IFS(NFSe_NC[[#This Row],[RETER INSS]]="NÃO",0,NFSe_NC[[#This Row],[RETER INSS]]="SIM",NFSe_NC[[#This Row],[VALOR NFS-e]]*11%)} -> 97.9 | O66: =E66-L66-N66 -> 747.6 | P66: OK | Q66: OK
A67: 1328 | B67: Fundo Especial da Procuradoria Geral do Estado do Paraná - FEPGE/PR | C67: 2930 | D67: 66 | E67: 2930 | F67: 41 | G67: 41069022213929397000142000000000006626010277231531 | H67: 46036 | I67: Emitida | K67: NÃO | L67: =_xlfn.IFS(NFSe_NC[[#This Row],[RETER ISS]]="NÃO",0,NFSe_NC[[#This Row],[RETER ISS]]="SIM",NFSe_NC[[#This Row],[VALOR NFS-e]]*5%) -> 0 | M67: NÃO | N67: {=_xlfn.IFS(NFSe_NC[[#This Row],[RETER INSS]]="NÃO",0,NFSe_NC[[#This Row],[RETER INSS]]="SIM",NFSe_NC[[#This Row],[VALOR NFS-e]]*11%)} -> 0 | O67: =E67-L67-N67 -> 2930 | P67: OK | Q67: OK
A68: 343 | B68: Alumisistem Esquadrias de Alumínio Ltda | C68: 12090 | D68: 67 | E68: 12090 | F68: 43 | G68: 41069022213929397000142000000000006726016472660317 | H68: 46036 | I68: Emitida | K68: NÃO | L68: =_xlfn.IFS(NFSe_NC[[#This Row],[RETER ISS]]="NÃO",0,NFSe_NC[[#This Row],[RETER ISS]]="SIM",NFSe_NC[[#This Row],[VALOR NFS-e]]*5%) -> 0 | M68: NÃO | N68: {=_xlfn.IFS(NFSe_NC[[#This Row],[RETER INSS]]="NÃO",0,NFSe_NC[[#This Row],[RETER INSS]]="SIM",NFSe_NC[[#This Row],[VALOR NFS-e]]*11%)} -> 0 | O68: =E68-L68-N68 -> 12090 | P68: OK | Q68: OK
A69: 1340 | B69: Lightera Latam S.A | C69: 890 | D69: 68 | E69: 890 | F69: 47 | G69: 41069022213929397000142000000000006826017818967298 | H69: 46036 | I69: Emitida | K69: NÃO | L69: =_xlfn.IFS(NFSe_NC[[#This Row],[RETER ISS]]="NÃO",0,NFSe_NC[[#This Row],[RETER ISS]]="SIM",NFSe_NC[[#This Row],[VALOR NFS-e]]*5%) -> 0 | M69: NÃO | N69: {=_xlfn.IFS(NFSe_NC[[#This Row],[RETER INSS]]="NÃO",0,NFSe_NC[[#This Row],[RETER INSS]]="SIM",NFSe_NC[[#This Row],[VALOR NFS-e]]*11%)} -> 0 | O69: =E69-L69-N69 -> 890 | P69: OK | Q69: OK
A70: 1174 | B70: Onet Engenharia e Manutenção Ltda | C70: 2243.6 | D70: 69 | E70: 890 | F70: 49 | G70: 41069022213929397000142000000000006926015692252080 | H70: 46037 | I70: Emitida | K70: NÃO | L70: =_xlfn.IFS(NFSe_NC[[#This Row],[RETER ISS]]="NÃO",0,NFSe_NC[[#This Row],[RETER ISS]]="SIM",NFSe_NC[[#This Row],[VALOR NFS-e]]*5%) -> 0 | M70: NÃO | N70: {=_xlfn.IFS(NFSe_NC[[#This Row],[RETER INSS]]="NÃO",0,NFSe_NC[[#This Row],[RETER INSS]]="SIM",NFSe_NC[[#This Row],[VALOR NFS-e]]*11%)} -> 0 | O70: =E70-L70-N70 -> 890 | P70: OK | Q70: OK
A71: 1193 | B71: In Haus Industrial e Serviços de Logistica S/A | C71: 27710.5 | D71: 70 | E71: 4290 | F71: 53 | G71: 41069022213929397000142000000000007026019996850370 | H71: 46038 | I71: Emitida | J71: Retenção ISS/INSS | K71: SIM | L71: =_xlfn.IFS(NFSe_NC[[#This Row],[RETER ISS]]="NÃO",0,NFSe_NC[[#This Row],[RETER ISS]]="SIM",NFSe_NC[[#This Row],[VALOR NFS-e]]*5%) -> 214.5 | M71: SIM | N71: {=_xlfn.IFS(NFSe_NC[[#This Row],[RETER INSS]]="NÃO",0,NFSe_NC[[#This Row],[RETER INSS]]="SIM",NFSe_NC[[#This Row],[VALOR NFS-e]]*11%)} -> 471.9 | O71: =E71-L71-N71 -> 3603.6 | P71: OK | Q71: OK
A72: 1375 | B72: Casc Administradora de Shopping Centers S.A. | C72: 2550 | D72: 71 | E72: 2550 | F72: 55 | G72: 41069022213929397000142000000000007126011807985840 | H72: 46041 | I72: Emitida | K72: NÃO | L72: =_xlfn.IFS(NFSe_NC[[#This Row],[RETER ISS]]="NÃO",0,NFSe_NC[[#This Row],[RETER ISS]]="SIM",NFSe_NC[[#This Row],[VALOR NFS-e]]*5%) -> 0 | M72: NÃO | N72: {=_xlfn.IFS(NFSe_NC[[#This Row],[RETER INSS]]="NÃO",0,NFSe_NC[[#This Row],[RETER INSS]]="SIM",NFSe_NC[[#This Row],[VALOR NFS-e]]*11%)} -> 0 | O72: =E72-L72-N72 -> 2550 | P72: OK | Q72: OK
A73: 1323 | B73: Ebanx Ltda | C73: 2100 | D73: 72 | E73: 450 | F73: 57 | G73: 41069022213929397000142000000000007226017361065979 | H73: 46041 | I73: Emitida | K73: NÃO | L73: =_xlfn.IFS(NFSe_NC[[#This Row],[RETER ISS]]="NÃO",0,NFSe_NC[[#This Row],[RETER ISS]]="SIM",NFSe_NC[[#This Row],[VALOR NFS-e]]*5%) -> 0 | M73: NÃO | N73: {=_xlfn.IFS(NFSe_NC[[#This Row],[RETER INSS]]="NÃO",0,NFSe_NC[[#This Row],[RETER INSS]]="SIM",NFSe_NC[[#This Row],[VALOR NFS-e]]*11%)} -> 0 | O73: =E73-L73-N73 -> 450 | P73: OK | Q73: OK
A74: 1130 | B74: Ebanx Ltda | C74: 6763 | D74: 73 | E74: 3690 | F74: 59 | G74: 41069022213929397000142000000000007326010820268382 | H74: 46041 | I74: Emitida | K74: NÃO | L74: =_xlfn.IFS(NFSe_NC[[#This Row],[RETER ISS]]="NÃO",0,NFSe_NC[[#This Row],[RETER ISS]]="SIM",NFSe_NC[[#This Row],[VALOR NFS-e]]*5%) -> 0 | M74: NÃO | N74: {=_xlfn.IFS(NFSe_NC[[#This Row],[RETER INSS]]="NÃO",0,NFSe_NC[[#This Row],[RETER INSS]]="SIM",NFSe_NC[[#This Row],[VALOR NFS-e]]*11%)} -> 0 | O74: =E74-L74-N74 -> 3690 | P74: OK | Q74: OK
A75: 1369 | B75: Hotel Curitiba Capital S/A | C75: 890 | D75: 74 | E75: 890 | F75: 61 | G75: 41069022213929397000142000000000007426019670696691 | H75: 46041 | I75: Emitida | K75: NÃO | L75: =_xlfn.IFS(NFSe_NC[[#This Row],[RETER ISS]]="NÃO",0,NFSe_NC[[#This Row],[RETER ISS]]="SIM",NFSe_NC[[#This Row],[VALOR NFS-e]]*5%) -> 0 | M75: NÃO | N75: {=_xlfn.IFS(NFSe_NC[[#This Row],[RETER INSS]]="NÃO",0,NFSe_NC[[#This Row],[RETER INSS]]="SIM",NFSe_NC[[#This Row],[VALOR NFS-e]]*11%)} -> 0 | O75: =E75-L75-N75 -> 890 | P75: OK | Q75: OK
A76: 916 | B76: Construtora Baggio Silveira Ltda | C76: 24146.1 | D76: 75 | E76: 11140 | F76: 63 | G76: 41069022213929397000142000000000007526019317457252 | H76: 46041 | I76: Emitida | J76: Retenção ISS/INSS | K76: SIM | L76: =_xlfn.IFS(NFSe_NC[[#This Row],[RETER ISS]]="NÃO",0,NFSe_NC[[#This Row],[RETER ISS]]="SIM",NFSe_NC[[#This Row],[VALOR NFS-e]]*5%) -> 557 | M76: SIM | N76: {=_xlfn.IFS(NFSe_NC[[#This Row],[RETER INSS]]="NÃO",0,NFSe_NC[[#This Row],[RETER INSS]]="SIM",NFSe_NC[[#This Row],[VALOR NFS-e]]*11%)} -> 1225.4 | O76: =E76-L76-N76 -> 9357.6 | P76: OK | Q76: OK
A77: 984 | B77: NB Engenharia Comércio e Construções Ltda | C77: 19700 | D77: 76 | E77: 7290 | F77: 65 | G77: 41069022213929397000142000000000007626014465230186 | H77: 46042 | I77: Cancelada | J77: Retenção ISS/INSS | K77: SIM | L77: =_xlfn.IFS(NFSe_NC[[#This Row],[RETER ISS]]="NÃO",0,NFSe_NC[[#This Row],[RETER ISS]]="SIM",NFSe_NC[[#This Row],[VALOR NFS-e]]*5%) -> 364.5 | M77: SIM | N77: {=_xlfn.IFS(NFSe_NC[[#This Row],[RETER INSS]]="NÃO",0,NFSe_NC[[#This Row],[RETER INSS]]="SIM",NFSe_NC[[#This Row],[VALOR NFS-e]]*11%)} -> 801.9 | O77: =E77-L77-N77 -> 6123.6 | P77: OK | Q77: OK
A78: 866 | B78: Fundação PIO XII | C78: 33440 | D78: 77 | E78: 11220 | F78: 67 | G78: 41069022213929397000142000000000007726011969211770 | H78: 46042 | I78: Cancelada | J78: Retenção ISS/INSS | K78: SIM | L78: =_xlfn.IFS(NFSe_NC[[#This Row],[RETER ISS]]="NÃO",0,NFSe_NC[[#This Row],[RETER ISS]]="SIM",NFSe_NC[[#This Row],[VALOR NFS-e]]*5%) -> 561 | M78: SIM | N78: {=_xlfn.IFS(NFSe_NC[[#This Row],[RETER INSS]]="NÃO",0,NFSe_NC[[#This Row],[RETER INSS]]="SIM",NFSe_NC[[#This Row],[VALOR NFS-e]]*11%)} -> 1234.2 | O78: =E78-L78-N78 -> 9424.8 | P78: OK | Q78: OK
A79: - | B79: Manusa do Brasil Comércio de Portas Automáticas Ltda | C79: 8279.04 | D79: 78 | E79: 8279.04 | F79: 69 | G79: 41069022213929397000142000000000007826013944670649 | H79: 46042 | I79: Emitida | J79: Comissão | K79: NÃO | L79: =_xlfn.IFS(NFSe_NC[[#This Row],[RETER ISS]]="NÃO",0,NFSe_NC[[#This Row],[RETER ISS]]="SIM",NFSe_NC[[#This Row],[VALOR NFS-e]]*5%) -> 0 | M79: NÃO | N79: {=_xlfn.IFS(NFSe_NC[[#This Row],[RETER INSS]]="NÃO",0,NFSe_NC[[#This Row],[RETER INSS]]="SIM",NFSe_NC[[#This Row],[VALOR NFS-e]]*11%)} -> 0 | O79: =E79-L79-N79 -> 8279.04 | P79: OK | Q79: OK
A80: 1414 | B80: Quick Burger Alimentos Ltda | C80: 801 | D80: 79 | E80: 801 | F80: 71 | G80: 41069022213929397000142000000000007926010516422263 | H80: 46044 | I80: Emitida | K80: NÃO | L80: =_xlfn.IFS(NFSe_NC[[#This Row],[RETER ISS]]="NÃO",0,NFSe_NC[[#This Row],[RETER ISS]]="SIM",NFSe_NC[[#This Row],[VALOR NFS-e]]*5%) -> 0 | M80: NÃO | N80: {=_xlfn.IFS(NFSe_NC[[#This Row],[RETER INSS]]="NÃO",0,NFSe_NC[[#This Row],[RETER INSS]]="SIM",NFSe_NC[[#This Row],[VALOR NFS-e]]*11%)} -> 0 | O80: =E80-L80-N80 -> 801 | P80: OK | Q80: OK
A81: 1412 | B81: Edifício Centro Empresarial Glaser | C81: 4299 | D81: 80 | E81: 1780 | F81: 78 | G81: 41069022213929397000142000000000008026012201971232 | H81: 46044 | I81: Emitida | K81: NÃO | L81: =_xlfn.IFS(NFSe_NC[[#This Row],[RETER ISS]]="NÃO",0,NFSe_NC[[#This Row],[RETER ISS]]="SIM",NFSe_NC[[#This Row],[VALOR NFS-e]]*5%) -> 0 | M81: NÃO | N81: {=_xlfn.IFS(NFSe_NC[[#This Row],[RETER INSS]]="NÃO",0,NFSe_NC[[#This Row],[RETER INSS]]="SIM",NFSe_NC[[#This Row],[VALOR NFS-e]]*11%)} -> 0 | O81: =E81-L81-N81 -> 1780 | P81: OK | Q81: OK
A82: 1292 | B82: Rinaldi Engenharia Civil Ltda | C82: 3735 | D82: 81 | E82: 1350 | F82: 80 | G82: 41069022213929397000142000000000008126010387076570 | H82: 46045 | I82: Cancelada | J82: Desconto R$ 60,42 | K82: NÃO | L82: =_xlfn.IFS(NFSe_NC[[#This Row],[RETER ISS]]="NÃO",0,NFSe_NC[[#This Row],[RETER ISS]]="SIM",NFSe_NC[[#This Row],[VALOR NFS-e]]*5%) -> 0 | M82: SIM | N82: {=_xlfn.IFS(NFSe_NC[[#This Row],[RETER INSS]]="NÃO",0,NFSe_NC[[#This Row],[RETER INSS]]="SIM",NFSe_NC[[#This Row],[VALOR NFS-e]]*11%)} -> 148.5 | O82: =E82-L82-N82 -> 1201.5 | P82: OK | Q82: OK
A83: 1292 | B83: Rinaldi Engenharia Civil Ltda | C83: 3735 | D83: 82 | E83: 1350 | F83: 83 | G83: 41069022213929397000142000000000008226015228992445 | H83: 46045 | I83: Substituida | J83: Retenção ISS/Desconto | K83: SIM | L83: =_xlfn.IFS(NFSe_NC[[#This Row],[RETER ISS]]="NÃO",0,NFSe_NC[[#This Row],[RETER ISS]]="SIM",NFSe_NC[[#This Row],[VALOR NFS-e]]*5%) -> 67.5 | M83: SIM | N83: {=_xlfn.IFS(NFSe_NC[[#This Row],[RETER INSS]]="NÃO",0,NFSe_NC[[#This Row],[RETER INSS]]="SIM",NFSe_NC[[#This Row],[VALOR NFS-e]]*11%)} -> 148.5 | O83: =E83-L83-N83 -> 1134 | P83: OK | Q83: OK
A84: 1409 | B84: Filial 51 - Condor Super Center Ltda | C84: 3874.5 | D84: 83 | E84: 2630 | F84: 85 | G84: 41069022213929397000142000000000008326019665415328 | H84: 46048 | I84: Emitida | J84: Retenção ISS | K84: SIM | L84: =_xlfn.IFS(NFSe_NC[[#This Row],[RETER ISS]]="NÃO",0,NFSe_NC[[#This Row],[RETER ISS]]="SIM",NFSe_NC[[#This Row],[VALOR NFS-e]]*5%) -> 131.5 | M84: NÃO | N84: {=_xlfn.IFS(NFSe_NC[[#This Row],[RETER INSS]]="NÃO",0,NFSe_NC[[#This Row],[RETER INSS]]="SIM",NFSe_NC[[#This Row],[VALOR NFS-e]]*11%)} -> 0 | O84: =E84-L84-N84 -> 2498.5 | P84: OK | Q84: OK
A85: 1416 | B85: Trelrium Comércio de Combustíveis e Conveniência Ltda | C85: 890 | D85: 84 | E85: 890 | F85: 87 | G85: 41069022213929397000142000000000008426010007549928 | H85: 46048 | I85: Emitida | K85: NÃO | L85: =_xlfn.IFS(NFSe_NC[[#This Row],[RETER ISS]]="NÃO",0,NFSe_NC[[#This Row],[RETER ISS]]="SIM",NFSe_NC[[#This Row],[VALOR NFS-e]]*5%) -> 0 | M85: NÃO | N85: {=_xlfn.IFS(NFSe_NC[[#This Row],[RETER INSS]]="NÃO",0,NFSe_NC[[#This Row],[RETER INSS]]="SIM",NFSe_NC[[#This Row],[VALOR NFS-e]]*11%)} -> 0 | O85: =E85-L85-N85 -> 890 | P85: OK | Q85: OK
A86: 1346 | B86: Onet Engenharia e Manutenção Ltda | C86: 2246 | D86: 85 | E86: 890 | F86: 89 | G86: 41069022213929397000142000000000008526014468721511 | H86: 46049 | I86: Emitida | K86: NÃO | L86: =_xlfn.IFS(NFSe_NC[[#This Row],[RETER ISS]]="NÃO",0,NFSe_NC[[#This Row],[RETER ISS]]="SIM",NFSe_NC[[#This Row],[VALOR NFS-e]]*5%) -> 0 | M86: NÃO | N86: {=_xlfn.IFS(NFSe_NC[[#This Row],[RETER INSS]]="NÃO",0,NFSe_NC[[#This Row],[RETER INSS]]="SIM",NFSe_NC[[#This Row],[VALOR NFS-e]]*11%)} -> 0 | O86: =E86-L86-N86 -> 890 | P86: OK | Q86: OK
A87: 1334 | B87: Mapa Comércio e Serviços em Portas Automáticas ltda | C87: 2689.79 | D87: 86 | E87: 2500 | F87: 91 | G87: 41069022213929397000142000000000008626016428623985 | H87: 46050 | I87: Substituida | K87: NÃO | L87: =_xlfn.IFS(NFSe_NC[[#This Row],[RETER ISS]]="NÃO",0,NFSe_NC[[#This Row],[RETER ISS]]="SIM",NFSe_NC[[#This Row],[VALOR NFS-e]]*5%) -> 0 | M87: NÃO | N87: {=_xlfn.IFS(NFSe_NC[[#This Row],[RETER INSS]]="NÃO",0,NFSe_NC[[#This Row],[RETER INSS]]="SIM",NFSe_NC[[#This Row],[VALOR NFS-e]]*11%)} -> 0 | O87: =E87-L87-N87 -> 2500 | P87: OK | Q87: OK
A88: 1292 | B88: Rinaldi Engenharia Civil Ltda | C88: 3735 | D88: 87 | E88: 1350 | F88: 93 | G88: 41069022213929397000142000000000008726015121715779 | H88: 46051 | I88: Emitida | J88: Retenção ISS/Desconto | K88: SIM | L88: =_xlfn.IFS(NFSe_NC[[#This Row],[RETER ISS]]="NÃO",0,NFSe_NC[[#This Row],[RETER ISS]]="SIM",NFSe_NC[[#This Row],[VALOR NFS-e]]*5%) -> 67.5 | M88: SIM | N88: {=_xlfn.IFS(NFSe_NC[[#This Row],[RETER INSS]]="NÃO",0,NFSe_NC[[#This Row],[RETER INSS]]="SIM",NFSe_NC[[#This Row],[VALOR NFS-e]]*11%)} -> 148.5 | O88: =E88-L88-N88 -> 1134 | P88: OK | Q88: OK
A89: 1450 | B89: Hexion Química do Brasil Ltda | C89: 890 | D89: 88 | E89: 890 | F89: 95 | G89: 41069022213929397000142000000000008826010174438900 | H89: 46051 | I89: Emitida | K89: NÃO | L89: =_xlfn.IFS(NFSe_NC[[#This Row],[RETER ISS]]="NÃO",0,NFSe_NC[[#This Row],[RETER ISS]]="SIM",NFSe_NC[[#This Row],[VALOR NFS-e]]*5%) -> 0 | M89: NÃO | N89: {=_xlfn.IFS(NFSe_NC[[#This Row],[RETER INSS]]="NÃO",0,NFSe_NC[[#This Row],[RETER INSS]]="SIM",NFSe_NC[[#This Row],[VALOR NFS-e]]*11%)} -> 0 | O89: =E89-L89-N89 -> 890 | P89: OK | Q89: OK
A90: 1431 | B90: Quick Burger Alimentos Ltda | C90: 2188.45 | D90: 89 | E90: 900 | F90: 97 | G90: 41069022213929397000142000000000008926010737971238 | H90: 46052 | I90: Emitida | K90: NÃO | L90: =_xlfn.IFS(NFSe_NC[[#This Row],[RETER ISS]]="NÃO",0,NFSe_NC[[#This Row],[RETER ISS]]="SIM",NFSe_NC[[#This Row],[VALOR NFS-e]]*5%) -> 0 | M90: NÃO | N90: {=_xlfn.IFS(NFSe_NC[[#This Row],[RETER INSS]]="NÃO",0,NFSe_NC[[#This Row],[RETER INSS]]="SIM",NFSe_NC[[#This Row],[VALOR NFS-e]]*11%)} -> 0 | O90: =E90-L90-N90 -> 900 | P90: OK | Q90: OK
A91: 1334 | B91: Mapa Comércio e Serviços em Portas Automáticas ltda | C91: 2689.79 | D91: 90 | E91: 2500 | F91: 99 | G91: 41069022213929397000142000000000009026013124288899 | H91: 46052 | I91: Emitida | K91: NÃO | L91: =_xlfn.IFS(NFSe_NC[[#This Row],[RETER ISS]]="NÃO",0,NFSe_NC[[#This Row],[RETER ISS]]="SIM",NFSe_NC[[#This Row],[VALOR NFS-e]]*5%) -> 0 | M91: NÃO | N91: {=_xlfn.IFS(NFSe_NC[[#This Row],[RETER INSS]]="NÃO",0,NFSe_NC[[#This Row],[RETER INSS]]="SIM",NFSe_NC[[#This Row],[VALOR NFS-e]]*11%)} -> 0 | O91: =E91-L91-N91 -> 2500 | P91: OK | Q91: OK
A92: 1411 | B92: JJGC Industria e Comercio de Materiais Dentarios S.A | C92: 890 | D92: 91 | E92: 890 | F92: 101 | G92: 41069022213929397000142000000000009126026731053032 | H92: 46055 | I92: Emitida | K92: NÃO | L92: =_xlfn.IFS(NFSe_NC[[#This Row],[RETER ISS]]="NÃO",0,NFSe_NC[[#This Row],[RETER ISS]]="SIM",NFSe_NC[[#This Row],[VALOR NFS-e]]*5%) -> 0 | M92: NÃO | N92: {=_xlfn.IFS(NFSe_NC[[#This Row],[RETER INSS]]="NÃO",0,NFSe_NC[[#This Row],[RETER INSS]]="SIM",NFSe_NC[[#This Row],[VALOR NFS-e]]*11%)} -> 0 | O92: =E92-L92-N92 -> 890 | P92: OK | Q92: OK
A93: 866 | B93: Fundação PIO XII | C93: 33440 | D93: 92 | E93: 11220 | F93: 103 | G93: 41069022213929397000142000000000009226022033686901 | H93: 46055 | I93: Emitida | J93: Retenção ISS/INSS | K93: SIM | L93: =_xlfn.IFS(NFSe_NC[[#This Row],[RETER ISS]]="NÃO",0,NFSe_NC[[#This Row],[RETER ISS]]="SIM",NFSe_NC[[#This Row],[VALOR NFS-e]]*5%) -> 561 | M93: SIM | N93: {=_xlfn.IFS(NFSe_NC[[#This Row],[RETER INSS]]="NÃO",0,NFSe_NC[[#This Row],[RETER INSS]]="SIM",NFSe_NC[[#This Row],[VALOR NFS-e]]*11%)} -> 1234.2 | O93: =E93-L93-N93 -> 9424.8 | P93: OK | Q93: OK
A94: 984 | B94: NB Engenharia Comércio e Construções Ltda | C94: 19700 | D94: 93 | E94: 7290 | F94: 105 | G94: 41069022213929397000142000000000009326021158183609 | H94: 46055 | I94: Emitida | J94: Retenção ISS/INSS | K94: SIM | L94: =_xlfn.IFS(NFSe_NC[[#This Row],[RETER ISS]]="NÃO",0,NFSe_NC[[#This Row],[RETER ISS]]="SIM",NFSe_NC[[#This Row],[VALOR NFS-e]]*5%) -> 364.5 | M94: SIM | N94: {=_xlfn.IFS(NFSe_NC[[#This Row],[RETER INSS]]="NÃO",0,NFSe_NC[[#This Row],[RETER INSS]]="SIM",NFSe_NC[[#This Row],[VALOR NFS-e]]*11%)} -> 801.9 | O94: =E94-L94-N94 -> 6123.6 | P94: OK | Q94: OK
A95: 641 | B95: 4L Serviços e Manutenções Ltda | C95: 16175 | D95: 94 | E95: 7030 | F95: 107 | G95: 41069022213929397000142000000000009426028280627231 | H95: 46055 | I95: Emitida | J95: Retenção ISS | K95: SIM | L95: =_xlfn.IFS(NFSe_NC[[#This Row],[RETER ISS]]="NÃO",0,NFSe_NC[[#This Row],[RETER ISS]]="SIM",NFSe_NC[[#This Row],[VALOR NFS-e]]*5%) -> 351.5 | M95: NÃO | N95: {=_xlfn.IFS(NFSe_NC[[#This Row],[RETER INSS]]="NÃO",0,NFSe_NC[[#This Row],[RETER INSS]]="SIM",NFSe_NC[[#This Row],[VALOR NFS-e]]*11%)} -> 0 | O95: =E95-L95-N95 -> 6678.5 | P95: OK | Q95: OK
A96: 1336 | B96: Centro Civico Apart Hotel Ltda | C96: 11806 | D96: 95 | E96: 3810 | F96: 1 | G96: 41069022213929397000142000000000009526020737961238 | H96: 46058 | I96: Emitida | K96: NÃO | L96: =_xlfn.IFS(NFSe_NC[[#This Row],[RETER ISS]]="NÃO",0,NFSe_NC[[#This Row],[RETER ISS]]="SIM",NFSe_NC[[#This Row],[VALOR NFS-e]]*5%) -> 0 | M96: NÃO | N96: {=_xlfn.IFS(NFSe_NC[[#This Row],[RETER INSS]]="NÃO",0,NFSe_NC[[#This Row],[RETER INSS]]="SIM",NFSe_NC[[#This Row],[VALOR NFS-e]]*11%)} -> 0 | O96: =E96-L96-N96 -> 3810 | P96: OK | Q96: OK
A97: 1496 | B97: Lanchonete Garcport Ltda | C97: 845.5 | D97: 96 | E97: 845.5 | F97: 2 | G97: 41069022213929397000142000000000009626028250080924 | H97: 46059 | I97: Emitida | K97: NÃO | L97: =_xlfn.IFS(NFSe_NC[[#This Row],[RETER ISS]]="NÃO",0,NFSe_NC[[#This Row],[RETER ISS]]="SIM",NFSe_NC[[#This Row],[VALOR NFS-e]]*5%) -> 0 | M97: NÃO | N97: {=_xlfn.IFS(NFSe_NC[[#This Row],[RETER INSS]]="NÃO",0,NFSe_NC[[#This Row],[RETER INSS]]="SIM",NFSe_NC[[#This Row],[VALOR NFS-e]]*11%)} -> 0 | O97: =E97-L97-N97 -> 845.5 | P97: OK | Q97: OK
A98: 1364 | B98: Neoortho Produtos Ortopédicos S.A | C98: 8863 | D98: 97 | E98: 4180 | F98: 4 | G98: 41069022213929397000142000000000009726024240921811 | H98: 46063 | I98: Cancelada | K98: NÃO | L98: =_xlfn.IFS(NFSe_NC[[#This Row],[RETER ISS]]="NÃO",0,NFSe_NC[[#This Row],[RETER ISS]]="SIM",NFSe_NC[[#This Row],[VALOR NFS-e]]*5%) -> 0 | M98: NÃO | N98: {=_xlfn.IFS(NFSe_NC[[#This Row],[RETER INSS]]="NÃO",0,NFSe_NC[[#This Row],[RETER INSS]]="SIM",NFSe_NC[[#This Row],[VALOR NFS-e]]*11%)} -> 0 | O98: =E98-L98-N98 -> 4180 | P98: OK | Q98: OK
A99: 1254 | B99: Cooperativa de Crédito, Poupança e Investimento Integração | C99: 8018 | D99: 98 | E99: 4340 | F99: 5 | G99: 41069022213929397000142000000000009826026384814540 | H99: 46064 | I99: Emitida | J99: Retenção ISS | K99: SIM | L99: =_xlfn.IFS(NFSe_NC[[#This Row],[RETER ISS]]="NÃO",0,NFSe_NC[[#This Row],[RETER ISS]]="SIM",NFSe_NC[[#This Row],[VALOR NFS-e]]*5%) -> 217 | M99: NÃO | N99: {=_xlfn.IFS(NFSe_NC[[#This Row],[RETER INSS]]="NÃO",0,NFSe_NC[[#This Row],[RETER INSS]]="SIM",NFSe_NC[[#This Row],[VALOR NFS-e]]*11%)} -> 0 | O99: =E99-L99-N99 -> 4123
A100: 1364 | B100: Neoortho Produtos Ortopédicos S.A | C100: 8863 | D100: 99 | E100: 4180 | F100: 6 | G100: 41069022213929397000142000000000009926029122495373 | H100: 46064 | I100: Emitida | K100: NÃO | L100: =_xlfn.IFS(NFSe_NC[[#This Row],[RETER ISS]]="NÃO",0,NFSe_NC[[#This Row],[RETER ISS]]="SIM",NFSe_NC[[#This Row],[VALOR NFS-e]]*5%) -> 0 | M100: NÃO | N100: {=_xlfn.IFS(NFSe_NC[[#This Row],[RETER INSS]]="NÃO",0,NFSe_NC[[#This Row],[RETER INSS]]="SIM",NFSe_NC[[#This Row],[VALOR NFS-e]]*11%)} -> 0 | O100: =E100-L100-N100 -> 4180
...

Sheet Nice and Clean 
A1: OS | B1: CLIENTE | C1: TOTAL OS | D1: NF-e | E1: VALOR | F1: NFS-e | G1: DPS | H1: VALOR SERVIÇO | I1: REF | J1: XML | K1: PDF | L1: OK | M1: STATUS
A2: 5 | B2: Coopavel | C2: 24836.25 | D2: 1095 | E2: 24836.25 | F2: - | G2: - | H2: - | I2: - | J2: ok | K2: ok | L2: OK
A3: 1147 | B3: Coopavel | C3: 10023.15 | D3: 1096 | E3: 5056.75 | F3: - | G3: - | H3: - | I3: - | J3: ok | K3: ok | L3: OK
A4: 380 | B4: Duotec | C4: 15070.5 | D4: 1098 | E4: 13030.5 | H4: 2040 | I4: 0483/25 | J4: ok | K4: ok | L4: WAIT | M4: Emitir NFS-e
A5: 1088 | B5: API SBE 46 | C5: 1320 | D5: 1099 | E5: 870 | F5: 1 | G5: 1 | H5: 450 | I5: - | J5: ok | K5: ok | L5: OK
A6: 1090 | B6: Graffo | C6: 5700 | D6: 1100 | E6: 5700 | F6: - | G6: - | H6: - | I6: - | J6: ok | K6: ok | L6: OK
A7: 1091 | B7: Doacir F | C7: 2906.24 | D7: 1101 | E7: 2256.24 | F7: 2 | G7: 2 | H7: 650 | I7: - | J7: ok | K7: ok | L7: OK
A8: 1094 | B8: Casa de Carnes | C8: 1029 | D8: 1102 | E8: 1029 | F8: - | G8: - | H8: - | I8: - | J8: ok | K8: ok | L8: OK

Sheet NF-e Nice
A1: OS | B1: CLIENTE | C1: TOTAL OS | D1: NF-e | E1: VALOR NF-e | F1: CFOP | G1: NATUREZA | H1: CHAVE | I1: EMISSÃO | J1: STATUS | K1: OBSERVAÇÕES | L1: PDF | M1: XML
A2: 1 | B2: Industria de Produtos Suínos Casa Velha Ltda | C2: 1010 | D2: 1090 | E2: 860 | F2: 6102 | G2: =VLOOKUP(F2,CFOP[],2,FALSE) -> Venda de mercadoria adquirida ou recebida de terceiros | H2: 41251002797390000106550010000010901293202511 | I2: 45951 | J2: Cancelada
A3: 444 | B3: Seara Alimentos Ltda | C3: 6873.6 | D3: 1091 | E3: 6873.6 | F3: 6102 | G3: =VLOOKUP(F3,CFOP[],2,FALSE) -> Venda de mercadoria adquirida ou recebida de terceiros | H3: 41251002797390000106550010000010911293202519 | I3: 45951 | J3: Emitida
A4: 443 | B4: Ledur e Ledur Comercio de Alimentos Ltda | C4: 4510.8 | D4: 1092 | E4: 4510.8 | F4: 6102 | G4: =VLOOKUP(F4,CFOP[],2,FALSE) -> Venda de mercadoria adquirida ou recebida de terceiros | H4: 41251002797390000106550010000010921293202516 | I4: 45951 | J4: Emitida
A5: 1 | B5: Industria de Produtos Suínos Casa Velha Ltda | C5: 1010 | D5: 1093 | E5: 1010 | F5: 6102 | G5: =VLOOKUP(F5,CFOP[],2,FALSE) -> Venda de mercadoria adquirida ou recebida de terceiros | H5: 41251002797390000106550010000010931293202513 | I5: 45951 | J5: Emitida
A6: - | B6: MetalFim Tratamentos de Superficie Ltda | C6: 3915 | D6: 1094 | E6: 3915 | F6: 5901 | G6: =VLOOKUP(F6,CFOP[],2,FALSE) -> Remessa para industrialização por encomenda | H6: 41251102797390000106550010000010941307202516 | I6: 45965 | J6: Emitida
A7: 5 | B7: Coopavel Cooperativa Agroindustrial | C7: 24836.25 | D7: 1095 | E7: 24836.25 | F7: 5102 | G7: =VLOOKUP(F7,CFOP[],2,FALSE) -> Venda de mercadoria adquirida ou recebida de terceiros | H7: 41251102797390000106550010000010951310202510 | I7: 45968 | J7: Emitida
A8: 1087 | B8: Coopavel Cooperativa Agroindustrial | C8: 5056.75 | D8: 1096 | E8: 5056.75 | F8: 5102 | G8: =VLOOKUP(F8,CFOP[],2,FALSE) -> Venda de mercadoria adquirida ou recebida de terceiros | H8: 41251102797390000106550010000010961310202518 | I8: 45968 | J8: Emitida
A9: 1147 | B9: Coopavel Cooperativa Agroindustrial | C9: 5056.75 | D9: 1097 | E9: 5056.75 | F9: 5102 | G9: =VLOOKUP(F9,CFOP[],2,FALSE) -> Venda de mercadoria adquirida ou recebida de terceiros | H9: 41251102797390000106550010000010971322202515 | I9: 45980 | J9: Emitida
A10: 380 | B10: Duotec Engenharia Ltda | C10: 15070.5 | D10: 1098 | E10: 13030.5 | F10: 5102 | G10: =VLOOKUP(F10,CFOP[],2,FALSE) -> Venda de mercadoria adquirida ou recebida de terceiros | H10: 41251102797390000106550010000010981328202514 | I10: 45986 | J10: Emitida
A11: 1088 | B11: API SPE 46 - Planejamento E Desenvolvimento De Empr. Imob. | C11: 1320 | D11: 1099 | E11: 870 | F11: 5102 | G11: =VLOOKUP(F11,CFOP[],2,FALSE) -> Venda de mercadoria adquirida ou recebida de terceiros | H11: 41251202797390000106550010000010991337202514 | I11: 45995 | J11: Emitida
A12: 1090 | B12: Graffo Paranaense de Embalagens Ltda | C12: 5700 | D12: 1100 | E12: 5700 | F12: 5102 | G12: =VLOOKUP(F12,CFOP[],2,FALSE) -> Venda de mercadoria adquirida ou recebida de terceiros | H12: 41251202797390000106550010000011001342202511 | I12: 46000 | J12: Emitida
A13: 1091 | B13: Doacir F Rodrigues da Silva & Cia Ltda | C13: 2906.24 | D13: 1101 | E13: 2256.24 | F13: 5102 | G13: =VLOOKUP(F13,CFOP[],2,FALSE) -> Venda de mercadoria adquirida ou recebida de terceiros | H13: 41251202797390000106550010000011011348202510 | I13: 46006 | J13: Emitida
A14: 1094 | B14: Casa de Carne da Gente Ltda | C14: 1029 | D14: 1102 | E14: 1029 | F14: 5102 | G14: =VLOOKUP(F14,CFOP[],2,FALSE) -> Venda de mercadoria adquirida ou recebida de terceiros | H14: 41260102797390000106550010000011021282026011 | I14: 46051 | J14: Emitida
A15: 1101 | B15: Filial 49 - Condor Super Center Ltda | C15: 2415.28 | D15: 1103 | E15: 1885.28 | F15: 5102 | G15: =VLOOKUP(F15,CFOP[],2,FALSE) -> Venda de mercadoria adquirida ou recebida de terceiros | H15: 41260202797390000106550010000011031412026025 | I15: 46064 | J15: Emitida
A16: 1105 | B16: Filial 52 - Condor Super Center Ltda | C16: 1515.85 | D16: 1104 | E16: 1515.85 | F16: 6102 | G16: =VLOOKUP(F16,CFOP[],2,FALSE) -> Venda de mercadoria adquirida ou recebida de terceiros | H16: 41260302797390000106550010000011041612026038 | I16: 46084 | J16: Emitida
A17: 1108 | B17: Bassano Di Grappo Fundo de Investimento Imobiliário | C17: 17184.47 | D17: 1105 | E17: 15534.47 | F17: 6102 | G17: =VLOOKUP(F17,CFOP[],2,FALSE) -> Venda de mercadoria adquirida ou recebida de terceiros | H17: 41260302797390000106550010000011051672026031 | I17: 46090 | J17: Emitida
A18: 1107 | B18: Marcos Cesar Borba Montagens Ltda | C18: 7567.8 | D18: 1106 | E18: 7567.8 | F18: 5102 | G18: =VLOOKUP(F18,CFOP[],2,FALSE) -> Venda de mercadoria adquirida ou recebida de terceiros | H18: 41260302797390000106550010000011061742026032 | I18: 46097 | J18: Emitida
... A21: 1112 | B21: Selection Locadora de Veículos Ltda | C21: 39151.51 | D21: 1109 | E21: 36401.51 | F21: 5102 | G21: =VLOOKUP(F21,CFOP[],2,FALSE) -> Venda de mercadoria adquirida ou recebida de terceiros | H21: 41260402797390000106550010000011091103202601 | I21: 46126 | J21: Emitida

Sheet NFS-e Nice
A1: OS | B1: CLIENTE | C1: TOTAL OS | D1: NFS-e | E1: VALOR NFS-e | F1: DPS | G1: CHAVE | H1: DATA | I1: STATUS | J1: OBSERVAÇÕES | K1: RETER ISS | L1: ISS | M1: RETER INSS | N1: INSS | O1: VALOR LIQUIDO | P1: PDFs | Q1: XML
A2: 1088 | B2: API SPE 46 - Planejamento E Desenvolvimento De Empr. Imob. | C2: 1320 | D2: 1 | E2: 450 | F2: 1 | G2: 41069022202797390000106000000000000125125288126319 | H2: 45995 | I2: Emitida | J2: Retenção INSS | K2: NÃO | L2: =_xlfn.IFS(NFSe_Nice[[#This Row],[RETER ISS]]="NÃO",0,NFSe_Nice[[#This Row],[RETER ISS]]="SIM",NFSe_Nice[[#This Row],[VALOR NFS-e]]*5%) -> 0 | M2: SIM | N2: {=_xlfn.IFS(NFSe_Nice[[#This Row],[RETER INSS]]="NÃO",0,NFSe_Nice[[#This Row],[RETER INSS]]="SIM",NFSe_Nice[[#This Row],[VALOR NFS-e]]*11%)} -> 49.5 | O2: =E2-L2-N2 -> 400.5 | P2: OK | Q2: OK
A3: 1091 | B3: Doacir F Rodrigues da Silva Cia Ltda | C3: 2906.24 | D3: 2 | E3: 650 | F3: 2 | G3: 41069022202797390000106000000000000225128353964296 | H3: 46006 | I3: Emitida | K3: NÃO | L3: =_xlfn.IFS(NFSe_Nice[[#This Row],[RETER ISS]]="NÃO",0,NFSe_Nice[[#This Row],[RETER ISS]]="SIM",NFSe_Nice[[#This Row],[VALOR NFS-e]]*5%) -> 0 | M3: NÃO | N3: {=_xlfn.IFS(NFSe_Nice[[#This Row],[RETER INSS]]="NÃO",0,NFSe_Nice[[#This Row],[RETER INSS]]="SIM",NFSe_Nice[[#This Row],[VALOR NFS-e]]*11%)} -> 0 | O3: =E3-L3-N3 -> 650 | P3: OK | Q3: OK
A4: 1101 | B4: Filial 49 - Condor Super Center Ltda | C4: 2415.28 | D4: 3 | E4: 530 | F4: 1 | G4: 41069022202797390000106000000000000326020647349057 | H4: 46064 | I4: Emitida | K4: NÃO | L4: =_xlfn.IFS(NFSe_Nice[[#This Row],[RETER ISS]]="NÃO",0,NFSe_Nice[[#This Row],[RETER ISS]]="SIM",NFSe_Nice[[#This Row],[VALOR NFS-e]]*5%) -> 0 | M4: NÃO | N4: {=_xlfn.IFS(NFSe_Nice[[#This Row],[RETER INSS]]="NÃO",0,NFSe_Nice[[#This Row],[RETER INSS]]="SIM",NFSe_Nice[[#This Row],[VALOR NFS-e]]*11%)} -> 0 | O4: =E4-L4-N4 -> 530
A5: 1108 | B5: Bassano Di Grappo Fundo de Investimento Imobiliário | C5: 17184.47 | D5: 4 | E5: 1650 | F5: 2 | G5: 41069022202797390000106000000000000426031604533300 | H5: 46090 | I5: Emitida | J5: Retenção INSS | K5: SIM | L5: =_xlfn.IFS(NFSe_Nice[[#This Row],[RETER ISS]]="NÃO",0,NFSe_Nice[[#This Row],[RETER ISS]]="SIM",NFSe_Nice[[#This Row],[VALOR NFS-e]]*5%) -> 82.5 | M5: SIM | N5: {=_xlfn.IFS(NFSe_Nice[[#This Row],[RETER INSS]]="NÃO",0,NFSe_Nice[[#This Row],[RETER INSS]]="SIM",NFSe_Nice[[#This Row],[VALOR NFS-e]]*11%)} -> 181.5 | O5: =E5-L5-N5 -> 1386
A6: 1117 | B6: JM Clean Comércio de Produtos de Higiene e Limpeza Ltda | C6: 9324.6 | D6: 5 | E6: 9324.6 | F6: 5 | G6: 41069022202797390000106000000000000526041117088175 | H6: 46119 | I6: Emitida | K6: NÃO | L6: =_xlfn.IFS(NFSe_Nice[[#This Row],[RETER ISS]]="NÃO",0,NFSe_Nice[[#This Row],[RETER ISS]]="SIM",NFSe_Nice[[#This Row],[VALOR NFS-e]]*5%) -> 0 | M6: NÃO | N6: {=_xlfn.IFS(NFSe_Nice[[#This Row],[RETER INSS]]="NÃO",0,NFSe_Nice[[#This Row],[RETER INSS]]="SIM",NFSe_Nice[[#This Row],[VALOR NFS-e]]*11%)} -> 0 | O6: =E6-L6-N6 -> 9324.6
A7: 1112 | B7: Selection Locadora de Veículos Ltda | C7: 39151.51 | D7: 6 | E7: 2750 | F7: 6 | G7: 41069022202797390000106000000000000626047957214659 | H7: 46127 | I7: Emitida | K7: NÃO | L7: =_xlfn.IFS(NFSe_Nice[[#This Row],[RETER ISS]]="NÃO",0,NFSe_Nice[[#This Row],[RETER ISS]]="SIM",NFSe_Nice[[#This Row],[VALOR NFS-e]]*5%) -> 0 | M7: NÃO | N7: {=_xlfn.IFS(NFSe_Nice[[#This Row],[RETER INSS]]="NÃO",0,NFSe_Nice[[#This Row],[RETER INSS]]="SIM",NFSe_Nice[[#This Row],[VALOR NFS-e]]*11%)} -> 0 | O7: =E7-L7-N7 -> 2750

Sheet Data
A1: CFOP | B1: DESCRIÇÃO | C1: REGIÃO | E1: PRODUTO | F1: VALOR M² | G1: PESO
A2: 1201 | B2: Devolução de venda de produção do estabelecimento | C2: Dentro do Estado | E2: Peça de PVC Cinza / Cristal / Cinza - Porta Flexdoor | F2: 790
A3: 1202 | B3: Devolução de venda de mercadoria adquirida ou recebida de terceiros | C3: Dentro do estado | E3: Porta Flexdoor Folha Simples (Até 1200mm Largura) | F3: 1590
A4: 2201 | B4: Devolução de venda de produção do estabelecimento | C4: Fora do Estado | E4: Porta Flexdoor Folha Dupla (De 1201mm a 3000mm) | F4: 1790
A5: 2202 | B5: Devolução de venda de mercadoria adquirida ou recebida de terceiros | C5: Fora do Estado | E5: Cortina em PVC Flexivel | F5: 260
A6: 5101 | B6: Venda de produção do estabelecimento | C6: Dentro do Estado | E6: Vidro Laminado Incolor 8mm | F6: 470 | G6: 20
A7: 5102 | B7: Venda de mercadoria adquirida ou recebida de terceiros | C7: Dentro do Estado | E7: Vidro Laminado Incolor 10mm | F7: 470 | G7: 25
A8: 5103 | B8: Venda de produção do estabelecimento efetuada fora do estabelecimento | C8: Dentro do Estado | E8: Vidro Laminado Incolor 12mm | F8: 570 | G8: 30
A9: 5107 | B9: Venda de produção do estabelecimento, destinada à Zona Franca de Manaus ou Áreas de Livre Comércio | C9: Dentro do Estado | E9: Vidro Laminado Incolor 15mm | F9: 620 | G9: 37.5
A10: 5403 | B10: Venda de mercadoria adquirida ou recebida de terceiros, sujeita ao regime de substituição tributária, cujo imposto já foi retido anteriormente ST | C10: Dentro do Estado | E10: Vidro Temperado Incolor 10mm | F10: 470 | G10: 25
A11: 5405 | B11: Venda de mercadoria adquirida ou recebida de terceiros, sujeita ao regime de substituição tributária, cujo imposto já foi retido anteriormente ST | C11: Dentro do Estado | E11: Vidro Temperado Incolor 12mm | F11: 470 | G11: 30
A12: 5901 | B12: Remessa para industrialização por encomenda | C12: Dentro do Estado | E12: Porta Social Clean ACM | F12: 1350
A13: 5916 | B13: Retorno de mercadoria recebida para conserto ou reparo | C13: Dentro do Estado | E13: Vidro Insulado 34mm | F13: 0 | G13: 85
A14: 5949 | B14: Outra saída de mercadoria ou prestação de serviço não especificado | C14: Dentro do Estado | E14: Folha em Policarbonato | F14: 1150
A15: 6102 | B15: Venda de mercadoria adquirida ou recebida de terceiros | C15: Fora do Estado
A16: 6107 | B16: Venda de produção do estabelecimento destinada a não contribuinte | C16: Fora do Estado
A17: 6108 | B17: Venda de mercadoria adquirida ou recebida de terceiros, destinada a não contribuinte | C17: Fora do Estado
A18: 6202 | B18: Devolução de venda de mercadoria adquirida ou recebida de terceiros | C18: Fora do Estado
A19: 6404 | B19: Venda de mercadoria adquirida ou recebida de terceiros, sujeita ao regime de substituição tributária, destinada a contribuinte do ICMS | C19: Fora do Estado
A20: 6901 | B20: Remessa para industrialização por encomenda | C20: Fora do Estado
A21: 6949 | B21: Outra saída de mercadoria ou prestação de serviço não especificado | C21: Fora do Estado

Sheet CSP
A1: 2026 | D1: Categoria | E1: 45962 | F1: 45992 | G1: 46023 | H1: 46054 | I1: 46082 | J1: Média Final
A2: Férias e 13° | B2: 30820.02 | D2: Salários | E2: 11549.99 | F2: 7440 | G2: 10826.07 | H2: 8218 | I2: 8387 | J2: =AVERAGE(E2:I2) -> 9284.212
A3: Férias e 13°/ Mês | B3: =B2/12 -> 2568.335 | D3: Benefícios | E3: 2043.08 | F3: 500.68 | G3: 3160.74 | H3: 8097.16 | I3: 314.74 | J3: =AVERAGE(E3:H3) -> 3450.415
A4: Férias e 13°/ Mês Nice | B4: 1497.96 | D4: Encargos | E4: 7106.74 | F4: 13898.09 | G4: 12241.4 | H4: 7534.82 | I4: 0 | J4: =AVERAGE(E4:H4) -> 10195.263
D5: Veículos | E5: 8766.89 | F5: 19447.76 | G5: 3169.01 | H5: 7793.48 | I5: 4492.59 | J5: =AVERAGE(E5:H5) -> 9794.285
A6: Folha Total NC | D6: Combustível | E6: 3504.56 | F6: 3486.23 | G6: 2373.87 | H6: 4155.27 | I6: 1376.97 | J6: =AVERAGE(E6:H6) -> 3379.9825
A7: Salários | B7: =J2 -> 9284.212 | D7: Salários Nice | E7: 9762.21 | F7: 5354.36 | G7: 9074.34 | H7: 4547.55 | I7: 7290.02 | J7: =AVERAGE(E7:I7) -> 7205.696
A8: Benefícios | B8: =J3 -> 3450.415 | D8: Benefícios Nice | E8: 0 | F8: 900 | G8: 1860 | H8: 1409 | I8: 0 | J8: =AVERAGE(F8:H8) -> 1389.6667
A9: Encargos | B9: =J4 -> 10195.263 | D9: Encargos Nice | E9: 4885.51 | F9: 8402.17 | G9: 6651.34 | H9: 5334.16 | I9: 1621 | J9: =AVERAGE(E9:H9) -> 6318.295
A10: Férias e 13° | B10: =B3 -> 2568.335 | D10: Veículos Nice | E10: 1196.82 | F10: 2720.07 | G10: 3123.93 | H10: 558.27 | I10: 558.27 | J10: =AVERAGE(E10:I10) -> 1631.472
A11: V_Folha_Total | B11: =SUM(B7:B10) -> 25498.225
A13: Folha Total Nice
A14: Salários | B14: =J7 -> 7205.696
A15: Benefícios | B15: =J8 -> 1389.6667
A16: Encargos | B16: =J9 -> 6318.295
A17: Férias e 13° | B17: =B4 -> 1497.96
A18: V_Folha_Total_Nice | B18: =SUM(B14:B17) -> 16411.618
A20: Frota Veículos
A21: Manutenção | B21: =J5 -> 9794.285
A22: Depreciação | B22: 1770
A23: V_Frota_Veiculos | B23: =SUM(B21:B22) -> 11564.285
A24: V_Frota_Veiculos_Nice | B24: =J10 -> 1631.472
A26: V_Folha_Total | B26: =B11+B18 -> 41909.842
A27: V_Frota_Veiculos | B27: =B23+B24 -> 13195.757
A28: H_Produtiva | B28: 770
A29: K_Valor_KM | B29: 0.85
A30: P_Imposto | B30: 0.1188
A31: S_Quant | B31: =Formulas!B18 -> 2
A32: S_Horas | B32: =Formulas!B19 -> 8
A33: S_Dist | B33: =Formulas!B20 -> 10
A34: S_Mat | B34: =Formulas!B21 -> 50
A36: CHH | B36: =B26/B28 -> 54.428366
A37: CHV | B37: =B27/B28 -> 17.137347

Sheet Serviços
A1: SERVIÇO | B1: QTDE | C1: V. UNIT | D1: V. TOTAL | E1: CLIENTE | F1: OS
A2: INSTALAÇÃO DE PORTA AUTOMÁTICA - HORÁRIO COMERCIAL | B2: 1.00 | C2: 3187.5 | D2: 3187.5 | E2: Nível Serviços Administrativos | F2: 1543
A3: ADEQUAÇÃO DE PORTA AUTOMÁTICA INDUSTRIAL | B3: 1.00 | C3: 6824.6 | D3: 6824.6 | E3: JM Clean | F3: 1556
A4: INSTALAÇÃO DE PORTA AUTOMÁTICA - HORÁRIO COMERCIAL | B4: 1.00 | C4: 2500 | D4: 2500 | E4: JM Clean | F4: 1556
A5: REVISÃO GERAL, REGULAGENS E AJUSTES EM PORTA AUTOMÁTICA - CÓDIGO 14.01 | B5: 1.00 | C5: 1280 | D5: 1280 | E5: Mondelez Brasil | F5: 1575
A6: INSTALAÇÃO DE PORTA AUTOMÁTICA - HORÁRIO COMERCIAL | B6: 1.00 | C6: 3000 | D6: 3000 | E6: Netcom Construtora | F6: 1590
A7: SERVIÇO DE PINTURA / ANODIZAÇÃO DE OPERADOR / FOLHA | B7: 1.00 | C7: 690 | D7: 690 | E7: Netcom Construtora | F7: 1590
A8: TRANSPORTE / FRETE | B8: 1.00 | C8: 790 | D8: 790 | E8: Netcom Construtora | F8: 1590
A9: TAXA DE DESLOCAMENTO | B9: 1.00 | C9: 630 | D9: 630 | E9: Auto Posto Transcap | F9: 1636
A10: REVISÃO GERAL, REGULAGENS E AJUSTES EM PORTA AUTOMÁTICA | B10: 1.00 | C10: 890 | D10: 890 | E10: LP Imóveis | F10: 1644
A11: INSTALAÇÃO DE PORTA AUTOMÁTICA - FORA DE HORÁRIO COMERCIAL | B11: 3.00 | C11: 1150 | D11: 3450 | E11: Cattalini Terminais Marítimos | F11: 1653
A12: TAXA DE DESLOCAMENTO | B12: 2.00 | C12: 500 | D12: 1000 | E12: Cattalini Terminais Marítimos | F12: 1653
A13: INSTALAÇÃO, REGULAGEM E AJUSTES | B13: 1.00 | C13: 750.5 | D13: 750.5 | E13: Trelrium Comercio de Combustiveis | F13: 1674
... A216: REVISÃO GERAL, REGULAGENS E AJUSTES EM PORTA AUTOMÁTICA | B216: 1.00 | C216: 790 | D216: 790 | E216: Araúz & Advogados | F216: 1799

Sheet Produtos
A1: PRODUTO | B1: UNIDADE | C1: QTDE | D1: NCM | E1: V. UNIT | F1: V. TOTAL | G1: CLIENTE | H1: OS
A2: BOTOEIRA DE ABERTURA - NO TOUCH | B2: (Un) | C2: 1 | D2: 85365090 | E2: 486 | F2: 486 | G2: Nível Serviços Administrativos | H2: 1543
A3: PORTA AUTOMÁTICA INDUSTRIAL DE ENVELOPAR | B3: (Un) | C3: 1 | D3: 39219019 | E3: 25500 | F3: 25500 | G3: Nível Serviços Administrativos | H3: 1543
A4: SISTEMA DE INTERTRAVAMENTO E INTERFACE | B4: (Un) | C4: 1 | D4: 90329010 | E4: 2834.3 | F4: 2834.3 | G4: Nível Serviços Administrativos | H4: 1543
A5: DETECTOR DE PROXIMIDADE - NC | B5: (Un) | C5: 1 | D5: 85261000 | E5: 622.25 | F5: 622.25 | G5: Netcom Construtora | H5: 1590
A6: VIDRO LAMINADO - INCOLOR/8MM | B6: (M²) | C6: 5.2 | D6: 70072900 | E6: 470 | F6: 2444 | G6: Netcom Construtora | H6: 1590
A7: VIGA ESTRUTURAL | B7: (Un) | C7: 1 | D7: 72163100 | E7: 1150 | F7: 1150 | G7: Netcom Construtora | H7: 1590
A8: BATERIA ACTIVA | B8: (Un) | C8: 1 | D8: 85068090 | E8: 682.5 | F8: 682.5 | G8: Mondelez Brasil | H8: 1594
A9: GUIA DE PISO T20 | B9: (Un) | C9: 2 | D9: 83024900 | E9: 190.4 | F9: 380.8 | G9: Mondelez Brasil | H9: 1594
A10: SELETOR OPTIMA+ | B10: (Un) | C10: 1 | D10: 85423190 | E10: 1016 | F10: 1016 | G10: Mondelez Brasil | H10: 1594
A11: GUIA DE PISO F20 / E20 | B11: (Un) | C11: 2 | D11: 83024900 | E11: 190.4 | F11: 380.8 | G11: Auto Posto Transcap | H11: 1636
A12: PERFIL POLICARBONATO - 10MM | B12: (Un) | C12: 2 | D12: 39204900 | E12: 190 | F12: 380 | G12: Auto Posto Transcap | H12: 1636
A13: BATERIA VISIO / VISIO+ | B13: (Un) | C13: 2 | D13: 85068090 | E13: 635 | F13: 1270 | G13: Mondelez Brasil | H13: 1655
... A471: BATERIA ACTIVA | B471: (Un) | C471: 1 | D471: 85068090 | E471: 695.5 | F471: 695.5 | G471: Araúz & Advogados | H471: 1799

Sheet Bases
A1: N° | B1: PRODUTO | C1: UNIDADE | D1: QTDE. | E1: NCM | F1: V. UNIT. | G1: V. TOTAL
A2: 1. | B2: A09002-230T-DS-0 - OPERADOR CENTRAL VISIO+ 100 | C2: (Un) | D2: 1 | E2: 84798999 | F2: 10900 | G2: 10900
A3: 2. | B3: A09993-E - TRINCO AUTOMÁTICO VISIO+ 100 | C3: (Un) | D3: 1 | E3: 83024900 | F3: 450 | G3: 450
A4: 3. | B4: EDRM05-E - RADAR MANUSA PLANAR | C4: (Un) | D4: 1 | E4: 85261000 | F4: 850 | G4: 850
A5: 4. | B5: A05038 - SENSOR HIBRÍDO DDS-B | C5: (Un) | D5: 1 | E5: 84798999 | F5: 1600 | G5: 1600
A6: 5. | B6: A05857-E - SELETOR OPTIMA+ | C6: (Un) | D6: 1 | E6: 85423190 | F6: 625 | G6: 625
A7: 6. | B7: ELG0001 - ESQUADRIA LINHA GOLD - MÓVEL | C7: (Un) | D7: 2 | E7: 76042100 | F7: 1980 | G7: 3960
A8: 7. | B8: ELG0002 - ESQUADRIA LINHA GOLD - FIXA | C8: (Un) | D8: 2 | E8: 76042100 | F8: 1980 | G8: 3960
A9: 8. | B9: VL0013 - VIDRO LAMINADO - NEUTRAL 14/8MM | C9: (M²) | D9: 8.5 | E9: 70072900 | F9: 480 | G9: 4080

Sheet Py Base
A1: Peso Max por Folha | B1: Lateral | C1: Central
A2: Visio + 100 | B2: 120 | C2: 90
A3: Visio + 125 | B3: 160 | C3: 120
A4: Visio+ 125 HD | B4: 293 | C4: 220
